[
  {
    "brandName": "ETIDOZE",
    "packSize": "10",
    "company": "TRIKO PHARMACEUTICALS",
    "brandMrp": "19.00",
    "yearMonth": "Dec-2025",
    "mrpPerUnit": "1.90"
  },
  {
    "brandName": "RESTFULL ET",
    "packSize": "10",
    "company": "LUPIN LTD",
    "brandMrp": "20.40",
    "yearMonth": "Dec-2025",
    "mrpPerUnit": "2.04"
  },
  {
    "brandName": "ETIMAX",
    "packSize": "10",
    "company": "THYONE HEALTH CARE",
    "brandMrp": "28.56",
    "yearMonth": "Dec-2025",
    "mrpPerUnit": "2.86"
  },
  {
    "brandName": "ETIZEX",
    "packSize": "10",
    "company": "TRIPADA HEALTHCARE PVT LTD",
    "brandMrp": "29.46",
    "yearMonth": "Dec-2025",
    "mrpPerUnit": "2.95"
  },
  {
    "brandName": "NITOCALM",
    "packSize": "10",
    "company": "LEEFORD HEALTHCARE",
    "brandMrp": "30.00",
    "yearMonth": "Dec-2025",
    "mrpPerUnit": "3.00"
  },
  {
    "brandName": "ETILOCK",
    "packSize": "10",
    "company": "TRIPADA LIFECARE PVT.LTD",
    "brandMrp": "31.25",
    "yearMonth": "Dec-2025",
    "mrpPerUnit": "3.13"
  },
  {
    "brandName": "SYLKAM",
    "packSize": "10",
    "company": "DR. REDDYS LABORATORIES LTD",
    "brandMrp": "31.35",
    "yearMonth": "Dec-2025",
    "mrpPerUnit": "3.14"
  },
  {
    "brandName": "ETIWELL",
    "packSize": "10",
    "company": "BIOS LAB PVT.LTD",
    "brandMrp": "32.67",
    "yearMonth": "Dec-2025",
    "mrpPerUnit": "3.27"
  },
  {
    "brandName": "ETIZEP",
    "packSize": "10",
    "company": "MICRO LABS LTD",
    "brandMrp": "32.80",
    "yearMonth": "Dec-2025",
    "mrpPerUnit": "3.28"
  },
  {
    "brandName": "TIZOCALM",
    "packSize": "10",
    "company": "NEXA WELLNESS PVT.LTD",
    "brandMrp": "32.81",
    "yearMonth": "Dec-2025",
    "mrpPerUnit": "3.28"
  },
  {
    "brandName": "ETNIZEX",
    "packSize": "10",
    "company": "TRIPADA HEALTHCARE PVT LTD",
    "brandMrp": "35.00",
    "yearMonth": "Dec-2025",
    "mrpPerUnit": "3.50"
  },
  {
    "brandName": "LAM ET",
    "packSize": "10",
    "company": "TAS MED (INDIA) PRIVATE LTD.",
    "brandMrp": "36.14",
    "yearMonth": "Dec-2025",
    "mrpPerUnit": "3.61"
  },
  {
    "brandName": "ETINAP",
    "packSize": "10",
    "company": "ICON LIFESCIENCES",
    "brandMrp": "36.56",
    "yearMonth": "Dec-2025",
    "mrpPerUnit": "3.66"
  },
  {
    "brandName": "ETISAFE",
    "packSize": "10",
    "company": "ORGANIC LABORATORIES",
    "brandMrp": "36.85",
    "yearMonth": "Dec-2025",
    "mrpPerUnit": "3.69"
  },
  {
    "brandName": "MACFRESH",
    "packSize": "10",
    "company": "MACLEODS PHARMACEUTICALS PVT.LTD",
    "brandMrp": "37.00",
    "yearMonth": "Dec-2025",
    "mrpPerUnit": "3.70"
  },
  {
    "brandName": "ETIPAX",
    "packSize": "10",
    "company": "RELIANCE FORMULATION PVT LTD",
    "brandMrp": "39.19",
    "yearMonth": "Dec-2025",
    "mrpPerUnit": "3.92"
  },
  {
    "brandName": "ETISURE",
    "packSize": "10",
    "company": "GENTECH HEALTCARE LTD",
    "brandMrp": "40.00",
    "yearMonth": "Dec-2025",
    "mrpPerUnit": "4.00"
  },
  {
    "brandName": "FONFRESH",
    "packSize": "10",
    "company": "FONCER PHARMA PVT. LTD",
    "brandMrp": "40.00",
    "yearMonth": "Dec-2025",
    "mrpPerUnit": "4.00"
  },
  {
    "brandName": "ETIZORAM",
    "packSize": "10",
    "company": "ARINNA LIFESCIENCES PVT. LTD",
    "brandMrp": "41.09",
    "yearMonth": "Dec-2025",
    "mrpPerUnit": "4.11"
  },
  {
    "brandName": "ETILAAM",
    "packSize": "10",
    "company": "INTAS PHARMACEUTICALS LTD",
    "brandMrp": "42.19",
    "yearMonth": "Dec-2025",
    "mrpPerUnit": "4.22"
  },
  {
    "brandName": "EZOLENT",
    "packSize": "10",
    "company": "TALENT INDIA",
    "brandMrp": "42.19",
    "yearMonth": "Dec-2025",
    "mrpPerUnit": "4.22"
  },
  {
    "brandName": "ETIZGO",
    "packSize": "10",
    "company": "SALAS PHARMA PVT.LTD",
    "brandMrp": "42.94",
    "yearMonth": "Dec-2025",
    "mrpPerUnit": "4.29"
  },
  {
    "brandName": "ETIMARK",
    "packSize": "10",
    "company": "UNIMARCK HEALTHCARE LTD",
    "brandMrp": "43.59",
    "yearMonth": "Dec-2025",
    "mrpPerUnit": "4.36"
  },
  {
    "brandName": "LAM ET",
    "packSize": "15",
    "company": "TAS MED (INDIA) PRIVATE LTD.",
    "brandMrp": "67.03",
    "yearMonth": "Dec-2025",
    "mrpPerUnit": "4.47"
  },
  {
    "brandName": "ELM (CNX)",
    "packSize": "10",
    "company": "CNX HEALTHCARE PVT LTD",
    "brandMrp": "45.00",
    "yearMonth": "Dec-2025",
    "mrpPerUnit": "4.50"
  },
  {
    "brandName": "ETOLAM",
    "packSize": "10",
    "company": "ALDE MEDI IMPEX",
    "brandMrp": "45.38",
    "yearMonth": "Dec-2025",
    "mrpPerUnit": "4.54"
  },
  {
    "brandName": "ETIGRAPH",
    "packSize": "10",
    "company": "SOLUMIKS HERBACEUTICALS LIMITED",
    "brandMrp": "45.68",
    "yearMonth": "Dec-2025",
    "mrpPerUnit": "4.57"
  },
  {
    "brandName": "ETIZEST",
    "packSize": "10",
    "company": "CONSERN PHARMA (P) LTD",
    "brandMrp": "46.00",
    "yearMonth": "Dec-2025",
    "mrpPerUnit": "4.60"
  },
  {
    "brandName": "MACFRESH",
    "packSize": "15",
    "company": "MACLEODS PHARMACEUTICALS PVT.LTD",
    "brandMrp": "69.60",
    "yearMonth": "Dec-2025",
    "mrpPerUnit": "4.64"
  },
  {
    "brandName": "ETZIC",
    "packSize": "10",
    "company": "ARRIENT HEALTHCARE PVT.LTD.",
    "brandMrp": "50.53",
    "yearMonth": "Dec-2025",
    "mrpPerUnit": "5.05"
  },
  {
    "brandName": "ETIDIP",
    "packSize": "10",
    "company": "ESWAR THERAPEUTICS PVT.LTD",
    "brandMrp": "60.94",
    "yearMonth": "Dec-2025",
    "mrpPerUnit": "6.09"
  },
  {
    "brandName": "SUPRABENZ",
    "packSize": "10",
    "company": "ALKEM LABORATORIES LTD.",
    "brandMrp": "62.30",
    "yearMonth": "Dec-2025",
    "mrpPerUnit": "6.23"
  },
  {
    "brandName": "LIAM",
    "packSize": "10",
    "company": "ALTEUS BIOGENICS PVT.LTD.",
    "brandMrp": "63.64",
    "yearMonth": "Dec-2025",
    "mrpPerUnit": "6.36"
  },
  {
    "brandName": "ETIREST",
    "packSize": "10",
    "company": "SUN PHARMA LABORATORIES LTD.",
    "brandMrp": "71.90",
    "yearMonth": "Dec-2025",
    "mrpPerUnit": "7.19"
  }
]