[
  {
    "hiddenId": "1521031520@251353@101123435@3854@101006@200730",
    "skuName": "ALBADIN 5 MG TABLET 10",
    "composition": "IVABRADINE TABLET 5 MG",
    "packSize": "10 TABLET",
    "dosageForm": "TABLET",
    "ceilingPrice": "-1",
    "company": "SALUD CARE (I) PVT LTD",
    "scheduleFlag": "0",
    "mrp": "138.75",
    "scheduleStatus": "Non-Scheduled",
    "yearMonth": "Dec-2025",
    "mrpPerUnit": "13.88"
  },
  {
    "hiddenId": "1521021067@291297@101114630@3854@101006@200730",
    "skuName": "BEAT HF 5 MG TABLET 10",
    "composition": "IVABRADINE TABLET 5 MG",
    "packSize": "10 TABLET",
    "dosageForm": "TABLET",
    "ceilingPrice": "-1",
    "company": "EMCURE PHARMACEUTICALS LTD",
    "scheduleFlag": "0",
    "mrp": "143.90",
    "scheduleStatus": "Non-Scheduled",
    "yearMonth": "Dec-2025",
    "mrpPerUnit": "14.39"
  },
  {
    "hiddenId": "1521027533@291295@101114630@3936@101006@200730",
    "skuName": "BEAT HF 7.5 MG TABLET 10",
    "composition": "IVABRADINE TABLET 7.5 MG",
    "packSize": "10 TABLET",
    "dosageForm": "TABLET",
    "ceilingPrice": "-1",
    "company": "EMCURE PHARMACEUTICALS LTD",
    "scheduleFlag": "0",
    "mrp": "150.00",
    "scheduleStatus": "Non-Scheduled",
    "yearMonth": "Dec-2025",
    "mrpPerUnit": "15.00"
  },
  {
    "hiddenId": "1521008392@194237@101105162@3854@101006@200730",
    "skuName": "BRADISWIFT 5 MG TABLET 10",
    "composition": "IVABRADINE TABLET 5 MG",
    "packSize": "10 TABLET",
    "dosageForm": "TABLET",
    "ceilingPrice": "-1",
    "company": "INDSWIFT LABORATORIES LTD.",
    "scheduleFlag": "0",
    "mrp": "137.16",
    "scheduleStatus": "Non-Scheduled",
    "yearMonth": "Dec-2025",
    "mrpPerUnit": "13.72"
  },
  {
    "hiddenId": "1521013868@315335@101241018@3854@101006@200730",
    "skuName": "CORABRAD 5 MG TABLET 10",
    "composition": "IVABRADINE TABLET 5 MG",
    "packSize": "10 TABLET",
    "dosageForm": "TABLET",
    "ceilingPrice": "-1",
    "company": "MANKIND PHARMACEUTICALS LTD.",
    "scheduleFlag": "0",
    "mrp": "177.19",
    "scheduleStatus": "Non-Scheduled",
    "yearMonth": "Dec-2025",
    "mrpPerUnit": "17.72"
  },
  {
    "hiddenId": "1521096726@348154@101241018@3854@101006@200730",
    "skuName": "CORABRAD 5 MG TABLET 15",
    "composition": "IVABRADINE TABLET 5 MG",
    "packSize": "15 TABLET",
    "dosageForm": "TABLET",
    "ceilingPrice": "-1",
    "company": "MANKIND PHARMACEUTICALS LTD.",
    "scheduleFlag": "0",
    "mrp": "321.58",
    "scheduleStatus": "Non-Scheduled",
    "yearMonth": "Dec-2025",
    "mrpPerUnit": "21.44"
  },
  {
    "hiddenId": "1521027368@315602@101241018@3936@101006@200730",
    "skuName": "CORABRAD 7.5 MG TABLET 10",
    "composition": "IVABRADINE TABLET 7.5 MG",
    "packSize": "10 TABLET",
    "dosageForm": "TABLET",
    "ceilingPrice": "-1",
    "company": "MANKIND PHARMACEUTICALS LTD.",
    "scheduleFlag": "0",
    "mrp": "219.36",
    "scheduleStatus": "Non-Scheduled",
    "yearMonth": "Dec-2025",
    "mrpPerUnit": "21.94"
  },
  {
    "hiddenId": "1521158050@702477@101244201@-1@101006@200730",
    "skuName": "CORABRAD OD TABLET 10",
    "composition": "IVABRADINE TABLET ",
    "packSize": "10 TABLET",
    "dosageForm": "TABLET",
    "ceilingPrice": "-1",
    "company": "MANKIND PHARMACEUTICALS LTD.",
    "scheduleFlag": "0",
    "mrp": "299.99",
    "scheduleStatus": "Non-Scheduled",
    "yearMonth": "Dec-2025",
    "mrpPerUnit": "30.00"
  },
  {
    "hiddenId": "1521059534@152893@101119540@3854@101006@200730",
    "skuName": "CORALAN 5 MG TABLET 14",
    "composition": "IVABRADINE TABLET 5 MG",
    "packSize": "14 TABLET",
    "dosageForm": "TABLET",
    "ceilingPrice": "-1",
    "company": "SERDIA PHARMACEUTICALS (INDIA) PVT. LTD.",
    "scheduleFlag": "0",
    "mrp": "333.51",
    "scheduleStatus": "Non-Scheduled",
    "yearMonth": "Dec-2025",
    "mrpPerUnit": "23.82"
  },
  {
    "hiddenId": "1521059568@152947@101119540@3936@101006@200730",
    "skuName": "CORALAN 7.5 MG TABLET 14",
    "composition": "IVABRADINE TABLET 7.5 MG",
    "packSize": "14 TABLET",
    "dosageForm": "TABLET",
    "ceilingPrice": "-1",
    "company": "SERDIA PHARMACEUTICALS (INDIA) PVT. LTD.",
    "scheduleFlag": "0",
    "mrp": "360.94",
    "scheduleStatus": "Non-Scheduled",
    "yearMonth": "Dec-2025",
    "mrpPerUnit": "25.78"
  },
  {
    "hiddenId": "1521097302@348447@101119540@2107@101006@200730",
    "skuName": "CORALAN OD 10 MG TABLET 10",
    "composition": "IVABRADINE TABLET 10 MG",
    "packSize": "10 TABLET",
    "dosageForm": "TABLET",
    "ceilingPrice": "-1",
    "company": "SERDIA PHARMACEUTICALS (INDIA) PVT. LTD.",
    "scheduleFlag": "0",
    "mrp": "328.97",
    "scheduleStatus": "Non-Scheduled",
    "yearMonth": "Dec-2025",
    "mrpPerUnit": "32.90"
  },
  {
    "hiddenId": "1521036530@317399@101139738@2107@101095@200730",
    "skuName": "INAPURE 10 MG TABLET ER 10",
    "composition": "IVABRADINE TABLET ER 10 MG",
    "packSize": "10 TABLET ER",
    "dosageForm": "TABLET ER",
    "ceilingPrice": "-1",
    "company": "SUN PHARMA LABORATORIES LTD.",
    "scheduleFlag": "0",
    "mrp": "411.56",
    "scheduleStatus": "Non-Scheduled",
    "yearMonth": "Dec-2025",
    "mrpPerUnit": "41.16"
  },
  {
    "hiddenId": "1521036542@319580@101139738@2744@101095@200730",
    "skuName": "INAPURE 15 MG TABLET ER 10",
    "composition": "IVABRADINE TABLET ER 15 MG",
    "packSize": "10 TABLET ER",
    "dosageForm": "TABLET ER",
    "ceilingPrice": "-1",
    "company": "SUN PHARMA LABORATORIES LTD.",
    "scheduleFlag": "0",
    "mrp": "439.00",
    "scheduleStatus": "Non-Scheduled",
    "yearMonth": "Dec-2025",
    "mrpPerUnit": "43.90"
  },
  {
    "hiddenId": "1521036568@122559@101139738@3854@101006@200730",
    "skuName": "INAPURE 5 MG TABLET 10",
    "composition": "IVABRADINE TABLET 5 MG",
    "packSize": "10 TABLET",
    "dosageForm": "TABLET",
    "ceilingPrice": "-1",
    "company": "SUN PHARMA LABORATORIES LTD.",
    "scheduleFlag": "0",
    "mrp": "261.56",
    "scheduleStatus": "Non-Scheduled",
    "yearMonth": "Dec-2025",
    "mrpPerUnit": "26.16"
  },
  {
    "hiddenId": "1521037306@248361@101140489@3854@101006@200730",
    "skuName": "IRBAN 5 MG TABLET 10",
    "composition": "IVABRADINE TABLET 5 MG",
    "packSize": "10 TABLET",
    "dosageForm": "TABLET",
    "ceilingPrice": "-1",
    "company": "GLENMARK PHARMACEUTICALS LTD.",
    "scheduleFlag": "0",
    "mrp": "147.19",
    "scheduleStatus": "Non-Scheduled",
    "yearMonth": "Dec-2025",
    "mrpPerUnit": "14.72"
  },
  {
    "hiddenId": "1521037205@325876@101140391@2107@101006@200730",
    "skuName": "IRBAN OD 10 MG TABLET 10",
    "composition": "IVABRADINE TABLET 10 MG",
    "packSize": "10 TABLET",
    "dosageForm": "TABLET",
    "ceilingPrice": "-1",
    "company": "GLENMARK PHARMACEUTICALS LTD.",
    "scheduleFlag": "0",
    "mrp": "250.00",
    "scheduleStatus": "Non-Scheduled",
    "yearMonth": "Dec-2025",
    "mrpPerUnit": "25.00"
  },
  {
    "hiddenId": "1521022981@329721@101140391@2744@101006@200730",
    "skuName": "IRBAN OD 15 MG TABLET 10",
    "composition": "IVABRADINE TABLET 15 MG",
    "packSize": "10 TABLET",
    "dosageForm": "TABLET",
    "ceilingPrice": "-1",
    "company": "GLENMARK PHARMACEUTICALS LTD.",
    "scheduleFlag": "0",
    "mrp": "300.00",
    "scheduleStatus": "Non-Scheduled",
    "yearMonth": "Dec-2025",
    "mrpPerUnit": "30.00"
  },
  {
    "hiddenId": "1521037914@184384@101141086@3854@101006@200730",
    "skuName": "IVABEAT 5 MG TABLET 10",
    "composition": "IVABRADINE TABLET 5 MG",
    "packSize": "10 TABLET",
    "dosageForm": "TABLET",
    "ceilingPrice": "-1",
    "company": "CIPLA LTD.",
    "scheduleFlag": "0",
    "mrp": "264.87",
    "scheduleStatus": "Non-Scheduled",
    "yearMonth": "Dec-2025",
    "mrpPerUnit": "26.49"
  },
  {
    "hiddenId": "1521035785@330516@101141086@2107@101006@200730",
    "skuName": "IVABEAT OD 10 MG TABLET 10",
    "composition": "IVABRADINE TABLET 10 MG",
    "packSize": "10 TABLET",
    "dosageForm": "TABLET",
    "ceilingPrice": "-1",
    "company": "CIPLA LTD.",
    "scheduleFlag": "0",
    "mrp": "385.69",
    "scheduleStatus": "Non-Scheduled",
    "yearMonth": "Dec-2025",
    "mrpPerUnit": "38.57"
  },
  {
    "hiddenId": "1521156853@339868@101141086@2744@101006@200730",
    "skuName": "IVABEAT OD 15 MG TABLET 10",
    "composition": "IVABRADINE TABLET 15 MG",
    "packSize": "10 TABLET",
    "dosageForm": "TABLET",
    "ceilingPrice": "-1",
    "company": "CIPLA LTD.",
    "scheduleFlag": "0",
    "mrp": "507.50",
    "scheduleStatus": "Non-Scheduled",
    "yearMonth": "Dec-2025",
    "mrpPerUnit": "50.75"
  },
  {
    "hiddenId": "1521092609@283359@101116396@3854@101006@200730",
    "skuName": "IVABID 5 MG TABLET 14",
    "composition": "IVABRADINE TABLET 5 MG",
    "packSize": "14 TABLET",
    "dosageForm": "TABLET",
    "ceilingPrice": "-1",
    "company": "ABBOTT HEALTHCARE PVT. LTD",
    "scheduleFlag": "0",
    "mrp": "431.75",
    "scheduleStatus": "Non-Scheduled",
    "yearMonth": "Dec-2025",
    "mrpPerUnit": "30.84"
  },
  {
    "hiddenId": "1521092610@305319@101116396@3936@101006@200730",
    "skuName": "IVABID 7.5 MG TABLET 14",
    "composition": "IVABRADINE TABLET 7.5 MG",
    "packSize": "14 TABLET",
    "dosageForm": "TABLET",
    "ceilingPrice": "-1",
    "company": "ABBOTT HEALTHCARE PVT. LTD",
    "scheduleFlag": "0",
    "mrp": "522.13",
    "scheduleStatus": "Non-Scheduled",
    "yearMonth": "Dec-2025",
    "mrpPerUnit": "37.30"
  },
  {
    "hiddenId": "1521092611@318773@101116396@2107@101006@200730",
    "skuName": "IVABID OD 10 MG TABLET 10",
    "composition": "IVABRADINE TABLET 10 MG",
    "packSize": "10 TABLET",
    "dosageForm": "TABLET",
    "ceilingPrice": "-1",
    "company": "ABBOTT HEALTHCARE PVT. LTD",
    "scheduleFlag": "0",
    "mrp": "480.38",
    "scheduleStatus": "Non-Scheduled",
    "yearMonth": "Dec-2025",
    "mrpPerUnit": "48.04"
  },
  {
    "hiddenId": "1521092612@320810@101116396@2744@101006@200730",
    "skuName": "IVABID OD 15 MG TABLET 10",
    "composition": "IVABRADINE TABLET 15 MG",
    "packSize": "10 TABLET",
    "dosageForm": "TABLET",
    "ceilingPrice": "-1",
    "company": "ABBOTT HEALTHCARE PVT. LTD",
    "scheduleFlag": "0",
    "mrp": "617.66",
    "scheduleStatus": "Non-Scheduled",
    "yearMonth": "Dec-2025",
    "mrpPerUnit": "61.77"
  },
  {
    "hiddenId": "1521037920@288937@101141100@3854@101006@200730",
    "skuName": "IVABLES 5 MG TABLET 15",
    "composition": "IVABRADINE TABLET 5 MG",
    "packSize": "15 TABLET",
    "dosageForm": "TABLET",
    "ceilingPrice": "-1",
    "company": "LLOYD HEALTHCARE PVT.LTD",
    "scheduleFlag": "0",
    "mrp": "284.53",
    "scheduleStatus": "Non-Scheduled",
    "yearMonth": "Dec-2025",
    "mrpPerUnit": "18.97"
  },
  {
    "hiddenId": "1521037921@232402@101141100@3936@101006@200730",
    "skuName": "IVABLES 7.5 MG TABLET 10",
    "composition": "IVABRADINE TABLET 7.5 MG",
    "packSize": "10 TABLET",
    "dosageForm": "TABLET",
    "ceilingPrice": "-1",
    "company": "LLOYD HEALTHCARE PVT.LTD",
    "scheduleFlag": "0",
    "mrp": "175.00",
    "scheduleStatus": "Non-Scheduled",
    "yearMonth": "Dec-2025",
    "mrpPerUnit": "17.50"
  },
  {
    "hiddenId": "1521037913@321895@101141100@2107@101006@200730",
    "skuName": "IVABLES OD 10 MG TABLET 10",
    "composition": "IVABRADINE TABLET 10 MG",
    "packSize": "10 TABLET",
    "dosageForm": "TABLET",
    "ceilingPrice": "-1",
    "company": "LLOYD HEALTHCARE PVT.LTD",
    "scheduleFlag": "0",
    "mrp": "409.40",
    "scheduleStatus": "Non-Scheduled",
    "yearMonth": "Dec-2025",
    "mrpPerUnit": "40.94"
  },
  {
    "hiddenId": "1521138077@247308@101233554@3854@101006@200730",
    "skuName": "IVABLOCK 5 MG TABLET 10",
    "composition": "IVABRADINE TABLET 5 MG",
    "packSize": "10 TABLET",
    "dosageForm": "TABLET",
    "ceilingPrice": "-1",
    "company": "OLCARE LTD",
    "scheduleFlag": "0",
    "mrp": "131.43",
    "scheduleStatus": "Non-Scheduled",
    "yearMonth": "Dec-2025",
    "mrpPerUnit": "13.14"
  },
  {
    "hiddenId": "1521037922@252080@101116400@3854@101006@200730",
    "skuName": "IVABRAD 5 MG TABLET 15",
    "composition": "IVABRADINE TABLET 5 MG",
    "packSize": "15 TABLET",
    "dosageForm": "TABLET",
    "ceilingPrice": "-1",
    "company": "LUPIN LTD",
    "scheduleFlag": "0",
    "mrp": "463.90",
    "scheduleStatus": "Non-Scheduled",
    "yearMonth": "Dec-2025",
    "mrpPerUnit": "30.93"
  },
  {
    "hiddenId": "1521037925@254144@101116400@3936@101006@200730",
    "skuName": "IVABRAD 7.5 MG TABLET 15",
    "composition": "IVABRADINE TABLET 7.5 MG",
    "packSize": "15 TABLET",
    "dosageForm": "TABLET",
    "ceilingPrice": "-1",
    "company": "LUPIN LTD",
    "scheduleFlag": "0",
    "mrp": "572.25",
    "scheduleStatus": "Non-Scheduled",
    "yearMonth": "Dec-2025",
    "mrpPerUnit": "38.15"
  },
  {
    "hiddenId": "1521038737@320076@101116400@2107@101195@200730",
    "skuName": "IVABRAD OD 10 MG TABLET PR 10",
    "composition": "IVABRADINE TABLET PR 10 MG",
    "packSize": "10 TABLET PR",
    "dosageForm": "TABLET PR",
    "ceilingPrice": "-1",
    "company": "LUPIN LTD",
    "scheduleFlag": "0",
    "mrp": "512.60",
    "scheduleStatus": "Non-Scheduled",
    "yearMonth": "Dec-2025",
    "mrpPerUnit": "51.26"
  },
  {
    "hiddenId": "1521066167@320077@101116400@2744@101006@200730",
    "skuName": "IVABRAD OD 15 MG TABLET 10",
    "composition": "IVABRADINE TABLET 15 MG",
    "packSize": "10 TABLET",
    "dosageForm": "TABLET",
    "ceilingPrice": "-1",
    "company": "LUPIN LTD",
    "scheduleFlag": "0",
    "mrp": "616.65",
    "scheduleStatus": "Non-Scheduled",
    "yearMonth": "Dec-2025",
    "mrpPerUnit": "61.67"
  },
  {
    "hiddenId": "1521068506@233785@101141105@3854@101006@200730",
    "skuName": "IVABRATCO 5 MG TABLET 10",
    "composition": "IVABRADINE TABLET 5 MG",
    "packSize": "10 TABLET",
    "dosageForm": "TABLET",
    "ceilingPrice": "-1",
    "company": "NATCO PHARMA LTD",
    "scheduleFlag": "0",
    "mrp": "149.53",
    "scheduleStatus": "Non-Scheduled",
    "yearMonth": "Dec-2025",
    "mrpPerUnit": "14.95"
  },
  {
    "hiddenId": "1521095454@344983@101141105@2107@101006@200730",
    "skuName": "IVABRATCO OD 10 MG TABLET 10",
    "composition": "IVABRADINE TABLET 10 MG",
    "packSize": "10 TABLET",
    "dosageForm": "TABLET",
    "ceilingPrice": "-1",
    "company": "NATCO PHARMA LTD",
    "scheduleFlag": "0",
    "mrp": "280.31",
    "scheduleStatus": "Non-Scheduled",
    "yearMonth": "Dec-2025",
    "mrpPerUnit": "28.03"
  },
  {
    "hiddenId": "1521149971@312520@101233560@3854@101006@200730",
    "skuName": "IVADINE 5 MG TABLET 10",
    "composition": "IVABRADINE TABLET 5 MG",
    "packSize": "10 TABLET",
    "dosageForm": "TABLET",
    "ceilingPrice": "-1",
    "company": "STERIS HEALTHCARE",
    "scheduleFlag": "0",
    "mrp": "103.75",
    "scheduleStatus": "Non-Scheduled",
    "yearMonth": "Dec-2025",
    "mrpPerUnit": "10.38"
  },
  {
    "hiddenId": "1521037926@331572@101141106@2107@101135@200730",
    "skuName": "IVADIN XR 10 MG TABLET XR 10",
    "composition": "IVABRADINE TABLET XR 10 MG",
    "packSize": "10 TABLET XR",
    "dosageForm": "TABLET XR",
    "ceilingPrice": "-1",
    "company": "ZUVENTUS HEALTHCARE LTD",
    "scheduleFlag": "0",
    "mrp": "384.65",
    "scheduleStatus": "Non-Scheduled",
    "yearMonth": "Dec-2025",
    "mrpPerUnit": "38.47"
  },
  {
    "hiddenId": "1521096856@345209@101191972@3854@101006@200730",
    "skuName": "IVAFORD 5 MG TABLET 15",
    "composition": "IVABRADINE TABLET 5 MG",
    "packSize": "15 TABLET",
    "dosageForm": "TABLET",
    "ceilingPrice": "-1",
    "company": "LEEFORD HEALTHCARE",
    "scheduleFlag": "0",
    "mrp": "234.30",
    "scheduleStatus": "Non-Scheduled",
    "yearMonth": "Dec-2025",
    "mrpPerUnit": "15.62"
  },
  {
    "hiddenId": "1521088986@335521@101188126@2107@101006@200730",
    "skuName": "IVALINK OD 10 MG TABLET 10",
    "composition": "IVABRADINE TABLET 10 MG",
    "packSize": "10 TABLET",
    "dosageForm": "TABLET",
    "ceilingPrice": "-1",
    "company": "LINCOLN PHARMACEUTICALS LTD",
    "scheduleFlag": "0",
    "mrp": "234.38",
    "scheduleStatus": "Non-Scheduled",
    "yearMonth": "Dec-2025",
    "mrpPerUnit": "23.44"
  },
  {
    "hiddenId": "1521159272@350523@101141113@2107@101006@200730",
    "skuName": "IVAMAC 10 MG TABLET 10",
    "composition": "IVABRADINE TABLET 10 MG",
    "packSize": "10 TABLET",
    "dosageForm": "TABLET",
    "ceilingPrice": "-1",
    "company": "MACLEODS PHARMACEUTICALS PVT.LTD",
    "scheduleFlag": "0",
    "mrp": "350.00",
    "scheduleStatus": "Non-Scheduled",
    "yearMonth": "Dec-2025",
    "mrpPerUnit": "35.00"
  },
  {
    "hiddenId": "1521037930@216320@101141113@3854@101006@200730",
    "skuName": "IVAMAC 5 MG TABLET 10",
    "composition": "IVABRADINE TABLET 5 MG",
    "packSize": "10 TABLET",
    "dosageForm": "TABLET",
    "ceilingPrice": "-1",
    "company": "MACLEODS PHARMACEUTICALS PVT.LTD",
    "scheduleFlag": "0",
    "mrp": "240.47",
    "scheduleStatus": "Non-Scheduled",
    "yearMonth": "Dec-2025",
    "mrpPerUnit": "24.05"
  },
  {
    "hiddenId": "1521098928@350522@101141113@3936@101006@200730",
    "skuName": "IVAMAC 7.5 MG TABLET 10",
    "composition": "IVABRADINE TABLET 7.5 MG",
    "packSize": "10 TABLET",
    "dosageForm": "TABLET",
    "ceilingPrice": "-1",
    "company": "MACLEODS PHARMACEUTICALS PVT.LTD",
    "scheduleFlag": "0",
    "mrp": "280.00",
    "scheduleStatus": "Non-Scheduled",
    "yearMonth": "Dec-2025",
    "mrpPerUnit": "28.00"
  },
  {
    "hiddenId": "1521097410@348240@101192299@2107@101006@200730",
    "skuName": "IVAMAC OD 10 MG TABLET 10",
    "composition": "IVABRADINE TABLET 10 MG",
    "packSize": "10 TABLET",
    "dosageForm": "TABLET",
    "ceilingPrice": "-1",
    "company": "MACLEODS PHARMACEUTICALS PVT.LTD",
    "scheduleFlag": "0",
    "mrp": "350.00",
    "scheduleStatus": "Non-Scheduled",
    "yearMonth": "Dec-2025",
    "mrpPerUnit": "35.00"
  },
  {
    "hiddenId": "1521151928@335522@101233569@3854@101006@200730",
    "skuName": "IVANGINA 5 MG TABLET 10",
    "composition": "IVABRADINE TABLET 5 MG",
    "packSize": "10 TABLET",
    "dosageForm": "TABLET",
    "ceilingPrice": "-1",
    "company": "PROQOL HEALTHCARE PVT.LTD",
    "scheduleFlag": "0",
    "mrp": "185.63",
    "scheduleStatus": "Non-Scheduled",
    "yearMonth": "Dec-2025",
    "mrpPerUnit": "18.56"
  },
  {
    "hiddenId": "1521093368@338642@101189767@2107@101006@200730",
    "skuName": "IVANICHE 10 MG TABLET 10",
    "composition": "IVABRADINE TABLET 10 MG",
    "packSize": "10 TABLET",
    "dosageForm": "TABLET",
    "ceilingPrice": "-1",
    "company": "ALNICHE LIFE SCIENCES PVT.LTD",
    "scheduleFlag": "0",
    "mrp": "350.00",
    "scheduleStatus": "Non-Scheduled",
    "yearMonth": "Dec-2025",
    "mrpPerUnit": "35.00"
  },
  {
    "hiddenId": "1521037931@126468@101141114@3854@101006@200730",
    "skuName": "IVANODE 5 MG TABLET 10",
    "composition": "IVABRADINE TABLET 5 MG",
    "packSize": "10 TABLET",
    "dosageForm": "TABLET",
    "ceilingPrice": "-1",
    "company": "TORRENT PHARMACEUTICALS LTD.",
    "scheduleFlag": "0",
    "mrp": "316.80",
    "scheduleStatus": "Non-Scheduled",
    "yearMonth": "Dec-2025",
    "mrpPerUnit": "31.68"
  },
  {
    "hiddenId": "1521091277@337833@101189582@2107@101006@200730",
    "skuName": "IVANODE OD 10 MG TABLET 10",
    "composition": "IVABRADINE TABLET 10 MG",
    "packSize": "10 TABLET",
    "dosageForm": "TABLET",
    "ceilingPrice": "-1",
    "company": "TORRENT PHARMACEUTICALS LTD.",
    "scheduleFlag": "0",
    "mrp": "422.40",
    "scheduleStatus": "Non-Scheduled",
    "yearMonth": "Dec-2025",
    "mrpPerUnit": "42.24"
  },
  {
    "hiddenId": "1521037932@325586@101141115@2107@101075@200730",
    "skuName": "IVAPACE 10 MG TABLET SR 10",
    "composition": "IVABRADINE TABLET SR 10 MG",
    "packSize": "10 TABLET SR",
    "dosageForm": "TABLET SR",
    "ceilingPrice": "-1",
    "company": "CORONA",
    "scheduleFlag": "0",
    "mrp": "200.00",
    "scheduleStatus": "Non-Scheduled",
    "yearMonth": "Dec-2025",
    "mrpPerUnit": "20.00"
  },
  {
    "hiddenId": "1521037933@325590@101141115@2744@101075@200730",
    "skuName": "IVAPACE 15 MG TABLET SR 10",
    "composition": "IVABRADINE TABLET SR 15 MG",
    "packSize": "10 TABLET SR",
    "dosageForm": "TABLET SR",
    "ceilingPrice": "-1",
    "company": "CORONA",
    "scheduleFlag": "0",
    "mrp": "300.00",
    "scheduleStatus": "Non-Scheduled",
    "yearMonth": "Dec-2025",
    "mrpPerUnit": "30.00"
  },
  {
    "hiddenId": "1521037934@266397@101141115@3854@101006@200730",
    "skuName": "IVAPACE 5 MG TABLET 10",
    "composition": "IVABRADINE TABLET 5 MG",
    "packSize": "10 TABLET",
    "dosageForm": "TABLET",
    "ceilingPrice": "-1",
    "company": "CORONA",
    "scheduleFlag": "0",
    "mrp": "215.81",
    "scheduleStatus": "Non-Scheduled",
    "yearMonth": "Dec-2025",
    "mrpPerUnit": "21.58"
  },
  {
    "hiddenId": "1521023153@266396@101141115@3936@101006@200730",
    "skuName": "IVAPACE 7.5 MG TABLET 10",
    "composition": "IVABRADINE TABLET 7.5 MG",
    "packSize": "10 TABLET",
    "dosageForm": "TABLET",
    "ceilingPrice": "-1",
    "company": "CORONA",
    "scheduleFlag": "0",
    "mrp": "247.03",
    "scheduleStatus": "Non-Scheduled",
    "yearMonth": "Dec-2025",
    "mrpPerUnit": "24.70"
  },
  {
    "hiddenId": "1521147792@287598@101233571@3854@101006@200730",
    "skuName": "IVAPRIDE 5 MG TABLET 10",
    "composition": "IVABRADINE TABLET 5 MG",
    "packSize": "10 TABLET",
    "dosageForm": "TABLET",
    "ceilingPrice": "-1",
    "company": "KNOLL HEALTHCARE PVT.LTD",
    "scheduleFlag": "0",
    "mrp": "144.38",
    "scheduleStatus": "Non-Scheduled",
    "yearMonth": "Dec-2025",
    "mrpPerUnit": "14.44"
  },
  {
    "hiddenId": "1521140178@287583@101233571@3936@101006@200730",
    "skuName": "IVAPRIDE 7.5 MG TABLET 10",
    "composition": "IVABRADINE TABLET 7.5 MG",
    "packSize": "10 TABLET",
    "dosageForm": "TABLET",
    "ceilingPrice": "-1",
    "company": "KNOLL HEALTHCARE PVT.LTD",
    "scheduleFlag": "0",
    "mrp": "210.00",
    "scheduleStatus": "Non-Scheduled",
    "yearMonth": "Dec-2025",
    "mrpPerUnit": "21.00"
  },
  {
    "hiddenId": "1521037935@240765@101141119@3854@101006@200730",
    "skuName": "IVAREST 5 MG TABLET 10",
    "composition": "IVABRADINE TABLET 5 MG",
    "packSize": "10 TABLET",
    "dosageForm": "TABLET",
    "ceilingPrice": "-1",
    "company": "ERGOS LIFE SCIENCES",
    "scheduleFlag": "0",
    "mrp": "231.00",
    "scheduleStatus": "Non-Scheduled",
    "yearMonth": "Dec-2025",
    "mrpPerUnit": "23.10"
  },
  {
    "hiddenId": "1521037936@303636@101141120@3854@101006@200730",
    "skuName": "IVASAFE 5 MG TABLET 10",
    "composition": "IVABRADINE TABLET 5 MG",
    "packSize": "10 TABLET",
    "dosageForm": "TABLET",
    "ceilingPrice": "-1",
    "company": "ACMEDIX PHARMA LLP",
    "scheduleFlag": "0",
    "mrp": "79.69",
    "scheduleStatus": "Non-Scheduled",
    "yearMonth": "Dec-2025",
    "mrpPerUnit": "7.97"
  },
  {
    "hiddenId": "1521149284@313875@101233576@3854@101006@200730",
    "skuName": "IVASMART 5 MG TABLET 10",
    "composition": "IVABRADINE TABLET 5 MG",
    "packSize": "10 TABLET",
    "dosageForm": "TABLET",
    "ceilingPrice": "-1",
    "company": "HEALING PHARMA INDIA PVT.LTD",
    "scheduleFlag": "0",
    "mrp": "86.25",
    "scheduleStatus": "Non-Scheduled",
    "yearMonth": "Dec-2025",
    "mrpPerUnit": "8.63"
  },
  {
    "hiddenId": "1521037937@125735@101141122@3854@101006@200730",
    "skuName": "IVAZINE 5 MG TABLET 10",
    "composition": "IVABRADINE TABLET 5 MG",
    "packSize": "10 TABLET",
    "dosageForm": "TABLET",
    "ceilingPrice": "-1",
    "company": "TORRENT PHARMACEUTICALS LTD.",
    "scheduleFlag": "0",
    "mrp": "307.00",
    "scheduleStatus": "Non-Scheduled",
    "yearMonth": "Dec-2025",
    "mrpPerUnit": "30.70"
  },
  {
    "hiddenId": "1521037938@125736@101141122@3936@101006@200730",
    "skuName": "IVAZINE 7.5 MG TABLET 10",
    "composition": "IVABRADINE TABLET 7.5 MG",
    "packSize": "10 TABLET",
    "dosageForm": "TABLET",
    "ceilingPrice": "-1",
    "company": "TORRENT PHARMACEUTICALS LTD.",
    "scheduleFlag": "0",
    "mrp": "232.49",
    "scheduleStatus": "Non-Scheduled",
    "yearMonth": "Dec-2025",
    "mrpPerUnit": "23.25"
  },
  {
    "hiddenId": "1521154709@348601@101242206@3854@101006@200730",
    "skuName": "RETROBRAD 5 MG TABLET 10",
    "composition": "IVABRADINE TABLET 5 MG",
    "packSize": "10 TABLET",
    "dosageForm": "TABLET",
    "ceilingPrice": "-1",
    "company": "EAST WEST PHARMA",
    "scheduleFlag": "0",
    "mrp": "215.63",
    "scheduleStatus": "Non-Scheduled",
    "yearMonth": "Dec-2025",
    "mrpPerUnit": "21.56"
  }
]