[
  {
    "brandName": "NEBRACIN",
    "packSize": "5",
    "company": "SUNWAYS (INDIA) PVT LTD",
    "brandMrp": "67.00",
    "yearMonth": "Dec-2025",
    "mrpPerUnit": "13.40"
  },
  {
    "brandName": "TOBRAM",
    "packSize": "5",
    "company": "PHARMTAK",
    "brandMrp": "85.00",
    "yearMonth": "Dec-2025",
    "mrpPerUnit": "17.00"
  },
  {
    "brandName": "TOCIN",
    "packSize": "5",
    "company": "OPTHO REMEDIES PVT.LTD",
    "brandMrp": "90.00",
    "yearMonth": "Dec-2025",
    "mrpPerUnit": "18.00"
  },
  {
    "brandName": "SAPTOB (SAPIENT)",
    "packSize": "3",
    "company": "SAPIENT",
    "brandMrp": "64.00",
    "yearMonth": "Dec-2025",
    "mrpPerUnit": "21.33"
  },
  {
    "brandName": "NAYANTOB",
    "packSize": "3",
    "company": "CHETHANA PHARMACEUTICALS",
    "brandMrp": "74.00",
    "yearMonth": "Dec-2025",
    "mrpPerUnit": "24.67"
  },
  {
    "brandName": "TOBRACID",
    "packSize": "3",
    "company": "ENTOD PHARMACEUTICALS LTD",
    "brandMrp": "89.53",
    "yearMonth": "Dec-2025",
    "mrpPerUnit": "29.84"
  },
  {
    "brandName": "TOJAWA",
    "packSize": "3",
    "company": "JAWA LABORATORIES",
    "brandMrp": "162.55",
    "yearMonth": "Dec-2025",
    "mrpPerUnit": "54.18"
  }
]