[
  {
    "brandName": "ISOTIX",
    "packSize": "10",
    "company": "PHOENIX LIFESCIENCES",
    "brandMrp": "110.00",
    "yearMonth": "Dec-2025",
    "mrpPerUnit": "11.00"
  },
  {
    "brandName": "SKINISTA",
    "packSize": "10",
    "company": "ENTOD PHARMACEUTICALS LTD",
    "brandMrp": "149.06",
    "yearMonth": "Dec-2025",
    "mrpPerUnit": "14.91"
  },
  {
    "brandName": "ISOGOLD (EUME)",
    "packSize": "10",
    "company": "EUMEDICA PHARMACEUTICALS",
    "brandMrp": "172.50",
    "yearMonth": "Dec-2025",
    "mrpPerUnit": "17.25"
  },
  {
    "brandName": "TYRET O",
    "packSize": "10",
    "company": "OMNI LIFE SCIENCES PVT LTD",
    "brandMrp": "204.38",
    "yearMonth": "Dec-2025",
    "mrpPerUnit": "20.44"
  }
]