[
  {
    "hiddenId": "1521090935@337558@101189463@3854@101006@200807",
    "skuName": "ACBISO 5 MG TABLET 10",
    "composition": "BISOPROLOL TABLET 5 MG",
    "packSize": "10 TABLET",
    "dosageForm": "TABLET",
    "ceilingPrice": "-1",
    "company": "ACMEDIX PHARMA LLP",
    "scheduleFlag": "0",
    "mrp": "29.00",
    "scheduleStatus": "Non-Scheduled",
    "yearMonth": "Dec-2025",
    "mrpPerUnit": "2.90"
  },
  {
    "hiddenId": "1521157504@701652@101243745@3311@101006@200807",
    "skuName": "AZKABIS 2.5 MG TABLET 15",
    "composition": "BISOPROLOL TABLET 2.5 MG",
    "packSize": "15 TABLET",
    "dosageForm": "TABLET",
    "ceilingPrice": "-1",
    "company": "AZKKA PHARMACEUTICALS PVT LTD",
    "scheduleFlag": "0",
    "mrp": "92.81",
    "scheduleStatus": "Non-Scheduled",
    "yearMonth": "Dec-2025",
    "mrpPerUnit": "6.19"
  },
  {
    "hiddenId": "1521157594@701679@101243745@3854@101006@200807",
    "skuName": "AZKABIS 5 MG TABLET 15",
    "composition": "BISOPROLOL TABLET 5 MG",
    "packSize": "15 TABLET",
    "dosageForm": "TABLET",
    "ceilingPrice": "-1",
    "company": "AZKKA PHARMACEUTICALS PVT LTD",
    "scheduleFlag": "0",
    "mrp": "92.81",
    "scheduleStatus": "Non-Scheduled",
    "yearMonth": "Dec-2025",
    "mrpPerUnit": "6.19"
  },
  {
    "hiddenId": "1521007064@225813@101103689@3311@101006@200807",
    "skuName": "BESICOR 2.5 MG TABLET 10",
    "composition": "BISOPROLOL TABLET 2.5 MG",
    "packSize": "10 TABLET",
    "dosageForm": "TABLET",
    "ceilingPrice": "-1",
    "company": "AJANTA PHARMA LTD",
    "scheduleFlag": "0",
    "mrp": "41.50",
    "scheduleStatus": "Non-Scheduled",
    "yearMonth": "Dec-2025",
    "mrpPerUnit": "4.15"
  },
  {
    "hiddenId": "1521006964@322334@101103689@3311@101006@200807",
    "skuName": "BESICOR 2.5 MG TABLET 15",
    "composition": "BISOPROLOL TABLET 2.5 MG",
    "packSize": "15 TABLET",
    "dosageForm": "TABLET",
    "ceilingPrice": "-1",
    "company": "AJANTA PHARMA LTD",
    "scheduleFlag": "0",
    "mrp": "98.44",
    "scheduleStatus": "Non-Scheduled",
    "yearMonth": "Dec-2025",
    "mrpPerUnit": "6.56"
  },
  {
    "hiddenId": "1521007065@225814@101103689@3854@101006@200807",
    "skuName": "BESICOR 5 MG TABLET 10",
    "composition": "BISOPROLOL TABLET 5 MG",
    "packSize": "10 TABLET",
    "dosageForm": "TABLET",
    "ceilingPrice": "-1",
    "company": "AJANTA PHARMA LTD",
    "scheduleFlag": "0",
    "mrp": "60.00",
    "scheduleStatus": "Non-Scheduled",
    "yearMonth": "Dec-2025",
    "mrpPerUnit": "6.00"
  },
  {
    "hiddenId": "1521007051@330357@101103689@3854@101006@200807",
    "skuName": "BESICOR 5 MG TABLET 15",
    "composition": "BISOPROLOL TABLET 5 MG",
    "packSize": "15 TABLET",
    "dosageForm": "TABLET",
    "ceilingPrice": "-1",
    "company": "AJANTA PHARMA LTD",
    "scheduleFlag": "0",
    "mrp": "146.72",
    "scheduleStatus": "Non-Scheduled",
    "yearMonth": "Dec-2025",
    "mrpPerUnit": "9.78"
  },
  {
    "hiddenId": "1521007068@212091@101103692@3311@101006@200807",
    "skuName": "BESOLOC 2.5 MG TABLET 10",
    "composition": "BISOPROLOL TABLET 2.5 MG",
    "packSize": "10 TABLET",
    "dosageForm": "TABLET",
    "ceilingPrice": "-1",
    "company": "EAST WEST PHARMA",
    "scheduleFlag": "0",
    "mrp": "55.58",
    "scheduleStatus": "Non-Scheduled",
    "yearMonth": "Dec-2025",
    "mrpPerUnit": "5.56"
  },
  {
    "hiddenId": "1521007072@290771@101103692@3854@101006@200807",
    "skuName": "BESOLOC 5 MG TABLET 10",
    "composition": "BISOPROLOL TABLET 5 MG",
    "packSize": "10 TABLET",
    "dosageForm": "TABLET",
    "ceilingPrice": "-1",
    "company": "EAST WEST PHARMA",
    "scheduleFlag": "0",
    "mrp": "32.50",
    "scheduleStatus": "Non-Scheduled",
    "yearMonth": "Dec-2025",
    "mrpPerUnit": "3.25"
  },
  {
    "hiddenId": "1521012017@313478@101104132@3311@101006@200807",
    "skuName": "BIBETA 2.5 MG TABLET 10",
    "composition": "BISOPROLOL TABLET 2.5 MG",
    "packSize": "10 TABLET",
    "dosageForm": "TABLET",
    "ceilingPrice": "-1",
    "company": "OPSISCARE LIFESCIENCSE PVT LTD",
    "scheduleFlag": "0",
    "mrp": "56.26",
    "scheduleStatus": "Non-Scheduled",
    "yearMonth": "Dec-2025",
    "mrpPerUnit": "5.63"
  },
  {
    "hiddenId": "1521007421@313479@101104132@3854@101006@200807",
    "skuName": "BIBETA 5 MG TABLET 10",
    "composition": "BISOPROLOL TABLET 5 MG",
    "packSize": "10 TABLET",
    "dosageForm": "TABLET",
    "ceilingPrice": "-1",
    "company": "OPSISCARE LIFESCIENCSE PVT LTD",
    "scheduleFlag": "0",
    "mrp": "65.63",
    "scheduleStatus": "Non-Scheduled",
    "yearMonth": "Dec-2025",
    "mrpPerUnit": "6.56"
  },
  {
    "hiddenId": "1521145142@291055@101104732@2401@101006@200807",
    "skuName": "BISBETA 1.25 MG TABLET 10",
    "composition": "BISOPROLOL TABLET 1.25 MG",
    "packSize": "10 TABLET",
    "dosageForm": "TABLET",
    "ceilingPrice": "-1",
    "company": "SHRRISHTI HEALTHCARE",
    "scheduleFlag": "0",
    "mrp": "15.00",
    "scheduleStatus": "Non-Scheduled",
    "yearMonth": "Dec-2025",
    "mrpPerUnit": "1.50"
  },
  {
    "hiddenId": "1521008025@150921@101104732@3311@101006@200807",
    "skuName": "BISBETA 2.5 MG TABLET 10",
    "composition": "BISOPROLOL TABLET 2.5 MG",
    "packSize": "10 TABLET",
    "dosageForm": "TABLET",
    "ceilingPrice": "-1",
    "company": "SHRRISHTI HEALTHCARE",
    "scheduleFlag": "0",
    "mrp": "25.00",
    "scheduleStatus": "Non-Scheduled",
    "yearMonth": "Dec-2025",
    "mrpPerUnit": "2.50"
  },
  {
    "hiddenId": "1521008026@150922@101104732@3854@101006@200807",
    "skuName": "BISBETA 5 MG TABLET 10",
    "composition": "BISOPROLOL TABLET 5 MG",
    "packSize": "10 TABLET",
    "dosageForm": "TABLET",
    "ceilingPrice": "-1",
    "company": "SHRRISHTI HEALTHCARE",
    "scheduleFlag": "0",
    "mrp": "28.57",
    "scheduleStatus": "Non-Scheduled",
    "yearMonth": "Dec-2025",
    "mrpPerUnit": "2.86"
  },
  {
    "hiddenId": "1521159721@704002@101243751@2401@101006@200807",
    "skuName": "BISCADO 1.25 MG TABLET 10",
    "composition": "BISOPROLOL TABLET 1.25 MG",
    "packSize": "10 TABLET",
    "dosageForm": "TABLET",
    "ceilingPrice": "-1",
    "company": "CADILA PHARMACEUTICALS LTD",
    "scheduleFlag": "0",
    "mrp": "45.94",
    "scheduleStatus": "Non-Scheduled",
    "yearMonth": "Dec-2025",
    "mrpPerUnit": "4.59"
  },
  {
    "hiddenId": "1521159401@704003@101243751@3311@101006@200807",
    "skuName": "BISCADO 2.5 MG TABLET 10",
    "composition": "BISOPROLOL TABLET 2.5 MG",
    "packSize": "10 TABLET",
    "dosageForm": "TABLET",
    "ceilingPrice": "-1",
    "company": "CADILA PHARMACEUTICALS LTD",
    "scheduleFlag": "0",
    "mrp": "60.94",
    "scheduleStatus": "Non-Scheduled",
    "yearMonth": "Dec-2025",
    "mrpPerUnit": "6.09"
  },
  {
    "hiddenId": "1521157389@702067@101243751@3854@101006@200807",
    "skuName": "BISCADO 5 MG TABLET 10",
    "composition": "BISOPROLOL TABLET 5 MG",
    "packSize": "10 TABLET",
    "dosageForm": "TABLET",
    "ceilingPrice": "-1",
    "company": "CADILA PHARMACEUTICALS LTD",
    "scheduleFlag": "0",
    "mrp": "89.06",
    "scheduleStatus": "Non-Scheduled",
    "yearMonth": "Dec-2025",
    "mrpPerUnit": "8.91"
  },
  {
    "hiddenId": "1521012223@64505@101104737@2107@101006@200807",
    "skuName": "BISELECT 10 MG TABLET 10",
    "composition": "BISOPROLOL TABLET 10 MG",
    "packSize": "10 TABLET",
    "dosageForm": "TABLET",
    "ceilingPrice": "-1",
    "company": "INTAS PHARMACEUTICALS LTD",
    "scheduleFlag": "0",
    "mrp": "98.91",
    "scheduleStatus": "Non-Scheduled",
    "yearMonth": "Dec-2025",
    "mrpPerUnit": "9.89"
  },
  {
    "hiddenId": "1521008027@64506@101104737@3311@101006@200807",
    "skuName": "BISELECT 2.5 MG TABLET 10",
    "composition": "BISOPROLOL TABLET 2.5 MG",
    "packSize": "10 TABLET",
    "dosageForm": "TABLET",
    "ceilingPrice": "-1",
    "company": "INTAS PHARMACEUTICALS LTD",
    "scheduleFlag": "0",
    "mrp": "41.72",
    "scheduleStatus": "Non-Scheduled",
    "yearMonth": "Dec-2025",
    "mrpPerUnit": "4.17"
  },
  {
    "hiddenId": "1521012225@64507@101104737@3854@101006@200807",
    "skuName": "BISELECT 5 MG TABLET 10",
    "composition": "BISOPROLOL TABLET 5 MG",
    "packSize": "10 TABLET",
    "dosageForm": "TABLET",
    "ceilingPrice": "-1",
    "company": "INTAS PHARMACEUTICALS LTD",
    "scheduleFlag": "0",
    "mrp": "52.50",
    "scheduleStatus": "Non-Scheduled",
    "yearMonth": "Dec-2025",
    "mrpPerUnit": "5.25"
  },
  {
    "hiddenId": "1521071993@310788@101172624@3311@101006@200807",
    "skuName": "BISOACE 2.5 MG TABLET 10",
    "composition": "BISOPROLOL TABLET 2.5 MG",
    "packSize": "10 TABLET",
    "dosageForm": "TABLET",
    "ceilingPrice": "-1",
    "company": "MOREPEN LABORATORIES LIMITED",
    "scheduleFlag": "0",
    "mrp": "7.50",
    "scheduleStatus": "Non-Scheduled",
    "yearMonth": "Dec-2025",
    "mrpPerUnit": "0.75"
  },
  {
    "hiddenId": "1521088684@310985@101172624@3854@101006@200807",
    "skuName": "BISOACE 5 MG TABLET 10",
    "composition": "BISOPROLOL TABLET 5 MG",
    "packSize": "10 TABLET",
    "dosageForm": "TABLET",
    "ceilingPrice": "-1",
    "company": "MOREPEN LABORATORIES LIMITED",
    "scheduleFlag": "0",
    "mrp": "10.96",
    "scheduleStatus": "Non-Scheduled",
    "yearMonth": "Dec-2025",
    "mrpPerUnit": "1.10"
  },
  {
    "hiddenId": "1521140272@349159@101229208@3311@101006@200807",
    "skuName": "BISOBEAT 2.5 MG TABLET 10",
    "composition": "BISOPROLOL TABLET 2.5 MG",
    "packSize": "10 TABLET",
    "dosageForm": "TABLET",
    "ceilingPrice": "-1",
    "company": "THYONE HEALTH CARE",
    "scheduleFlag": "0",
    "mrp": "58.13",
    "scheduleStatus": "Non-Scheduled",
    "yearMonth": "Dec-2025",
    "mrpPerUnit": "5.81"
  },
  {
    "hiddenId": "1521140271@349157@101229208@3854@101006@200807",
    "skuName": "BISOBEAT 5 MG TABLET 10",
    "composition": "BISOPROLOL TABLET 5 MG",
    "packSize": "10 TABLET",
    "dosageForm": "TABLET",
    "ceilingPrice": "-1",
    "company": "THYONE HEALTH CARE",
    "scheduleFlag": "0",
    "mrp": "73.13",
    "scheduleStatus": "Non-Scheduled",
    "yearMonth": "Dec-2025",
    "mrpPerUnit": "7.31"
  },
  {
    "hiddenId": "1521091139@337948@101189476@3311@101006@200807",
    "skuName": "BISOBIS 2.5 MG TABLET 10",
    "composition": "BISOPROLOL TABLET 2.5 MG",
    "packSize": "10 TABLET",
    "dosageForm": "TABLET",
    "ceilingPrice": "-1",
    "company": "CORONA",
    "scheduleFlag": "0",
    "mrp": "49.88",
    "scheduleStatus": "Non-Scheduled",
    "yearMonth": "Dec-2025",
    "mrpPerUnit": "4.99"
  },
  {
    "hiddenId": "1521091140@337947@101189476@3854@101006@200807",
    "skuName": "BISOBIS 5 MG TABLET 10",
    "composition": "BISOPROLOL TABLET 5 MG",
    "packSize": "10 TABLET",
    "dosageForm": "TABLET",
    "ceilingPrice": "-1",
    "company": "CORONA",
    "scheduleFlag": "0",
    "mrp": "49.88",
    "scheduleStatus": "Non-Scheduled",
    "yearMonth": "Dec-2025",
    "mrpPerUnit": "4.99"
  },
  {
    "hiddenId": "1521159268@703526@101244827@3311@101006@200807",
    "skuName": "BISOCAP 2.5 MG TABLET 15",
    "composition": "BISOPROLOL TABLET 2.5 MG",
    "packSize": "15 TABLET",
    "dosageForm": "TABLET",
    "ceilingPrice": "-1",
    "company": "NEOBEAT HEALTHCARE PVT.LTD",
    "scheduleFlag": "0",
    "mrp": "84.38",
    "scheduleStatus": "Non-Scheduled",
    "yearMonth": "Dec-2025",
    "mrpPerUnit": "5.63"
  },
  {
    "hiddenId": "1521158798@703527@101244827@3854@101006@200807",
    "skuName": "BISOCAP 5 MG TABLET 15",
    "composition": "BISOPROLOL TABLET 5 MG",
    "packSize": "15 TABLET",
    "dosageForm": "TABLET",
    "ceilingPrice": "-1",
    "company": "NEOBEAT HEALTHCARE PVT.LTD",
    "scheduleFlag": "0",
    "mrp": "103.13",
    "scheduleStatus": "Non-Scheduled",
    "yearMonth": "Dec-2025",
    "mrpPerUnit": "6.88"
  },
  {
    "hiddenId": "1521054435@5669@101157378@3311@101006@200807",
    "skuName": "BISOCAR 2.5 MG TABLET 10",
    "composition": "BISOPROLOL TABLET 2.5 MG",
    "packSize": "10 TABLET",
    "dosageForm": "TABLET",
    "ceilingPrice": "-1",
    "company": "RUSAN HEALTHCARE PVT. LTD",
    "scheduleFlag": "0",
    "mrp": "29.44",
    "scheduleStatus": "Non-Scheduled",
    "yearMonth": "Dec-2025",
    "mrpPerUnit": "2.94"
  },
  {
    "hiddenId": "1521054458@5670@101157378@3854@101006@200807",
    "skuName": "BISOCAR 5 MG TABLET 10",
    "composition": "BISOPROLOL TABLET 5 MG",
    "packSize": "10 TABLET",
    "dosageForm": "TABLET",
    "ceilingPrice": "-1",
    "company": "RUSAN HEALTHCARE PVT. LTD",
    "scheduleFlag": "0",
    "mrp": "39.19",
    "scheduleStatus": "Non-Scheduled",
    "yearMonth": "Dec-2025",
    "mrpPerUnit": "3.92"
  },
  {
    "hiddenId": "1521141480@350577@101229210@3311@101006@200807",
    "skuName": "BISOCUT 2.5 MG TABLET 15",
    "composition": "BISOPROLOL TABLET 2.5 MG",
    "packSize": "15 TABLET",
    "dosageForm": "TABLET",
    "ceilingPrice": "-1",
    "company": "ORRIS PHARMACEUTICALS",
    "scheduleFlag": "0",
    "mrp": "70.00",
    "scheduleStatus": "Non-Scheduled",
    "yearMonth": "Dec-2025",
    "mrpPerUnit": "4.67"
  },
  {
    "hiddenId": "1521141490@350575@101229210@3854@101006@200807",
    "skuName": "BISOCUT 5 MG TABLET 15",
    "composition": "BISOPROLOL TABLET 5 MG",
    "packSize": "15 TABLET",
    "dosageForm": "TABLET",
    "ceilingPrice": "-1",
    "company": "ORRIS PHARMACEUTICALS",
    "scheduleFlag": "0",
    "mrp": "112.50",
    "scheduleStatus": "Non-Scheduled",
    "yearMonth": "Dec-2025",
    "mrpPerUnit": "7.50"
  },
  {
    "hiddenId": "1521054430@311613@101226257@3311@101006@200807",
    "skuName": "BISODER 2.5 MG TABLET 10",
    "composition": "BISOPROLOL TABLET 2.5 MG",
    "packSize": "10 TABLET",
    "dosageForm": "TABLET",
    "ceilingPrice": "-1",
    "company": "ELDER PROJECTS LIMITED",
    "scheduleFlag": "0",
    "mrp": "44.63",
    "scheduleStatus": "Non-Scheduled",
    "yearMonth": "Dec-2025",
    "mrpPerUnit": "4.46"
  },
  {
    "hiddenId": "1521099867@307725@101226257@3854@101006@200807",
    "skuName": "BISODER 5 MG TABLET 10",
    "composition": "BISOPROLOL TABLET 5 MG",
    "packSize": "10 TABLET",
    "dosageForm": "TABLET",
    "ceilingPrice": "-1",
    "company": "ELDER PROJECTS LIMITED",
    "scheduleFlag": "0",
    "mrp": "96.80",
    "scheduleStatus": "Non-Scheduled",
    "yearMonth": "Dec-2025",
    "mrpPerUnit": "9.68"
  },
  {
    "hiddenId": "1521152469@340103@101229212@3311@101006@200807",
    "skuName": "BISODIX 2.5 MG TABLET 10",
    "composition": "BISOPROLOL TABLET 2.5 MG",
    "packSize": "10 TABLET",
    "dosageForm": "TABLET",
    "ceilingPrice": "-1",
    "company": "UCARDIX PHARMACEUTICALS PVT LTD",
    "scheduleFlag": "0",
    "mrp": "84.30",
    "scheduleStatus": "Non-Scheduled",
    "yearMonth": "Dec-2025",
    "mrpPerUnit": "8.43"
  },
  {
    "hiddenId": "1521152471@340104@101229212@3854@101006@200807",
    "skuName": "BISODIX 5 MG TABLET 10",
    "composition": "BISOPROLOL TABLET 5 MG",
    "packSize": "10 TABLET",
    "dosageForm": "TABLET",
    "ceilingPrice": "-1",
    "company": "UCARDIX PHARMACEUTICALS PVT LTD",
    "scheduleFlag": "0",
    "mrp": "98.40",
    "scheduleStatus": "Non-Scheduled",
    "yearMonth": "Dec-2025",
    "mrpPerUnit": "9.84"
  },
  {
    "hiddenId": "1521135407@9999998104@101225478@3311@101006@200807",
    "skuName": "BISODREN 2.5 MG TABLET 10",
    "composition": "BISOPROLOL TABLET 2.5 MG",
    "packSize": "10 TABLET",
    "dosageForm": "TABLET",
    "ceilingPrice": "-1",
    "company": "FUSION HEALTHCARE PVT LTD",
    "scheduleFlag": "0",
    "mrp": "51.00",
    "scheduleStatus": "Non-Scheduled",
    "yearMonth": "Dec-2025",
    "mrpPerUnit": "5.10"
  },
  {
    "hiddenId": "1521135408@9999998103@101225478@3854@101006@200807",
    "skuName": "BISODREN 5 MG TABLET 10",
    "composition": "BISOPROLOL TABLET 5 MG",
    "packSize": "10 TABLET",
    "dosageForm": "TABLET",
    "ceilingPrice": "-1",
    "company": "FUSION HEALTHCARE PVT LTD",
    "scheduleFlag": "0",
    "mrp": "69.00",
    "scheduleStatus": "Non-Scheduled",
    "yearMonth": "Dec-2025",
    "mrpPerUnit": "6.90"
  },
  {
    "hiddenId": "1521155248@9999994817@101242280@2401@101006@200807",
    "skuName": "BISODUCE 1.25 MG TABLET 10",
    "composition": "BISOPROLOL TABLET 1.25 MG",
    "packSize": "10 TABLET",
    "dosageForm": "TABLET",
    "ceilingPrice": "-1",
    "company": "MACLEODS PHARMACEUTICALS PVT.LTD",
    "scheduleFlag": "0",
    "mrp": "56.24",
    "scheduleStatus": "Non-Scheduled",
    "yearMonth": "Dec-2025",
    "mrpPerUnit": "5.62"
  },
  {
    "hiddenId": "1521155245@9999994816@101242280@3311@101006@200807",
    "skuName": "BISODUCE 2.5 MG TABLET 10",
    "composition": "BISOPROLOL TABLET 2.5 MG",
    "packSize": "10 TABLET",
    "dosageForm": "TABLET",
    "ceilingPrice": "-1",
    "company": "MACLEODS PHARMACEUTICALS PVT.LTD",
    "scheduleFlag": "0",
    "mrp": "74.06",
    "scheduleStatus": "Non-Scheduled",
    "yearMonth": "Dec-2025",
    "mrpPerUnit": "7.41"
  },
  {
    "hiddenId": "1521155242@9999994815@101242280@3854@101006@200807",
    "skuName": "BISODUCE 5 MG TABLET 10",
    "composition": "BISOPROLOL TABLET 5 MG",
    "packSize": "10 TABLET",
    "dosageForm": "TABLET",
    "ceilingPrice": "-1",
    "company": "MACLEODS PHARMACEUTICALS PVT.LTD",
    "scheduleFlag": "0",
    "mrp": "93.75",
    "scheduleStatus": "Non-Scheduled",
    "yearMonth": "Dec-2025",
    "mrpPerUnit": "9.38"
  },
  {
    "hiddenId": "1521103306@353892@101195248@3311@101006@200807",
    "skuName": "BISOFIG 2.5 MG TABLET 10",
    "composition": "BISOPROLOL TABLET 2.5 MG",
    "packSize": "10 TABLET",
    "dosageForm": "TABLET",
    "ceilingPrice": "-1",
    "company": "CIPLA LTD.",
    "scheduleFlag": "0",
    "mrp": "56.71",
    "scheduleStatus": "Non-Scheduled",
    "yearMonth": "Dec-2025",
    "mrpPerUnit": "5.67"
  },
  {
    "hiddenId": "1521103410@353894@101195248@3854@101006@200807",
    "skuName": "BISOFIG 5 MG TABLET 10",
    "composition": "BISOPROLOL TABLET 5 MG",
    "packSize": "10 TABLET",
    "dosageForm": "TABLET",
    "ceilingPrice": "-1",
    "company": "CIPLA LTD.",
    "scheduleFlag": "0",
    "mrp": "82.50",
    "scheduleStatus": "Non-Scheduled",
    "yearMonth": "Dec-2025",
    "mrpPerUnit": "8.25"
  },
  {
    "hiddenId": "1521152371@339489@101229214@3311@101006@200807",
    "skuName": "BISOGARD 2.5 MG TABLET 10",
    "composition": "BISOPROLOL TABLET 2.5 MG",
    "packSize": "10 TABLET",
    "dosageForm": "TABLET",
    "ceilingPrice": "-1",
    "company": "STERIS HEALTHCARE",
    "scheduleFlag": "0",
    "mrp": "44.10",
    "scheduleStatus": "Non-Scheduled",
    "yearMonth": "Dec-2025",
    "mrpPerUnit": "4.41"
  },
  {
    "hiddenId": "1521152372@339490@101229214@3854@101006@200807",
    "skuName": "BISOGARD 5 MG TABLET 10",
    "composition": "BISOPROLOL TABLET 5 MG",
    "packSize": "10 TABLET",
    "dosageForm": "TABLET",
    "ceilingPrice": "-1",
    "company": "STERIS HEALTHCARE",
    "scheduleFlag": "0",
    "mrp": "54.90",
    "scheduleStatus": "Non-Scheduled",
    "yearMonth": "Dec-2025",
    "mrpPerUnit": "5.49"
  },
  {
    "hiddenId": "1521008029@196159@101240928@3311@101006@200807",
    "skuName": "BISOHEART 2.5 MG TABLET 10",
    "composition": "BISOPROLOL TABLET 2.5 MG",
    "packSize": "10 TABLET",
    "dosageForm": "TABLET",
    "ceilingPrice": "-1",
    "company": "MANKIND PHARMACEUTICALS LTD.",
    "scheduleFlag": "0",
    "mrp": "69.41",
    "scheduleStatus": "Non-Scheduled",
    "yearMonth": "Dec-2025",
    "mrpPerUnit": "6.94"
  },
  {
    "hiddenId": "1521012227@196160@101240928@3854@101006@200807",
    "skuName": "BISOHEART 5 MG TABLET 10",
    "composition": "BISOPROLOL TABLET 5 MG",
    "packSize": "10 TABLET",
    "dosageForm": "TABLET",
    "ceilingPrice": "-1",
    "company": "MANKIND PHARMACEUTICALS LTD.",
    "scheduleFlag": "0",
    "mrp": "96.42",
    "scheduleStatus": "Non-Scheduled",
    "yearMonth": "Dec-2025",
    "mrpPerUnit": "9.64"
  },
  {
    "hiddenId": "1521133711@9999999905@101245863@2107@101006@200807",
    "skuName": "BISOJOY 10 MG TABLET 10",
    "composition": "BISOPROLOL TABLET 10 MG",
    "packSize": "10 TABLET",
    "dosageForm": "TABLET",
    "ceilingPrice": "-1",
    "company": "ZYDUS HEALTHCARE LTD.",
    "scheduleFlag": "0",
    "mrp": "51.56",
    "scheduleStatus": "Non-Scheduled",
    "yearMonth": "Dec-2025",
    "mrpPerUnit": "5.16"
  },
  {
    "hiddenId": "1521133703@9999999906@101245863@2401@101006@200807",
    "skuName": "BISOJOY 1.25 MG TABLET 10",
    "composition": "BISOPROLOL TABLET 1.25 MG",
    "packSize": "10 TABLET",
    "dosageForm": "TABLET",
    "ceilingPrice": "-1",
    "company": "ZYDUS HEALTHCARE LTD.",
    "scheduleFlag": "0",
    "mrp": "51.56",
    "scheduleStatus": "Non-Scheduled",
    "yearMonth": "Dec-2025",
    "mrpPerUnit": "5.16"
  },
  {
    "hiddenId": "1521133715@9999999904@101245863@3311@101006@200807",
    "skuName": "BISOJOY 2.5 MG TABLET 10",
    "composition": "BISOPROLOL TABLET 2.5 MG",
    "packSize": "10 TABLET",
    "dosageForm": "TABLET",
    "ceilingPrice": "-1",
    "company": "ZYDUS HEALTHCARE LTD.",
    "scheduleFlag": "0",
    "mrp": "51.56",
    "scheduleStatus": "Non-Scheduled",
    "yearMonth": "Dec-2025",
    "mrpPerUnit": "5.16"
  },
  {
    "hiddenId": "1521133700@9999999903@101245863@3854@101006@200807",
    "skuName": "BISOJOY 5 MG TABLET 10",
    "composition": "BISOPROLOL TABLET 5 MG",
    "packSize": "10 TABLET",
    "dosageForm": "TABLET",
    "ceilingPrice": "-1",
    "company": "ZYDUS HEALTHCARE LTD.",
    "scheduleFlag": "0",
    "mrp": "51.56",
    "scheduleStatus": "Non-Scheduled",
    "yearMonth": "Dec-2025",
    "mrpPerUnit": "5.16"
  },
  {
    "hiddenId": "1521012218@317750@101104739@3311@101006@200807",
    "skuName": "BISOLONG 2.5 MG TABLET 10",
    "composition": "BISOPROLOL TABLET 2.5 MG",
    "packSize": "10 TABLET",
    "dosageForm": "TABLET",
    "ceilingPrice": "-1",
    "company": "MICRO LABS LTD",
    "scheduleFlag": "0",
    "mrp": "53.40",
    "scheduleStatus": "Non-Scheduled",
    "yearMonth": "Dec-2025",
    "mrpPerUnit": "5.34"
  },
  {
    "hiddenId": "1521008028@317749@101104739@3854@101006@200807",
    "skuName": "BISOLONG 5 MG TABLET 10",
    "composition": "BISOPROLOL TABLET 5 MG",
    "packSize": "10 TABLET",
    "dosageForm": "TABLET",
    "ceilingPrice": "-1",
    "company": "MICRO LABS LTD",
    "scheduleFlag": "0",
    "mrp": "78.75",
    "scheduleStatus": "Non-Scheduled",
    "yearMonth": "Dec-2025",
    "mrpPerUnit": "7.88"
  },
  {
    "hiddenId": "1521026159@321194@101105454@2107@101006@200807",
    "skuName": "BISONEXT 10 MG TABLET 15",
    "composition": "BISOPROLOL TABLET 10 MG",
    "packSize": "15 TABLET",
    "dosageForm": "TABLET",
    "ceilingPrice": "-1",
    "company": "LUPIN LTD",
    "scheduleFlag": "0",
    "mrp": "244.75",
    "scheduleStatus": "Non-Scheduled",
    "yearMonth": "Dec-2025",
    "mrpPerUnit": "16.32"
  },
  {
    "hiddenId": "1521012417@321195@101105454@3311@101006@200807",
    "skuName": "BISONEXT 2.5 MG TABLET 15",
    "composition": "BISOPROLOL TABLET 2.5 MG",
    "packSize": "15 TABLET",
    "dosageForm": "TABLET",
    "ceilingPrice": "-1",
    "company": "LUPIN LTD",
    "scheduleFlag": "0",
    "mrp": "120.15",
    "scheduleStatus": "Non-Scheduled",
    "yearMonth": "Dec-2025",
    "mrpPerUnit": "8.01"
  },
  {
    "hiddenId": "1521053288@321196@101105454@3854@101006@200807",
    "skuName": "BISONEXT 5 MG TABLET 15",
    "composition": "BISOPROLOL TABLET 5 MG",
    "packSize": "15 TABLET",
    "dosageForm": "TABLET",
    "ceilingPrice": "-1",
    "company": "LUPIN LTD",
    "scheduleFlag": "0",
    "mrp": "162.75",
    "scheduleStatus": "Non-Scheduled",
    "yearMonth": "Dec-2025",
    "mrpPerUnit": "10.85"
  },
  {
    "hiddenId": "1521147610@281027@101229215@3311@101006@200807",
    "skuName": "BISONOL 2.5 MG TABLET 10",
    "composition": "BISOPROLOL TABLET 2.5 MG",
    "packSize": "10 TABLET",
    "dosageForm": "TABLET",
    "ceilingPrice": "-1",
    "company": "KNOLL HEALTHCARE PVT.LTD",
    "scheduleFlag": "0",
    "mrp": "39.00",
    "scheduleStatus": "Non-Scheduled",
    "yearMonth": "Dec-2025",
    "mrpPerUnit": "3.90"
  },
  {
    "hiddenId": "1521147643@281089@101229215@3854@101006@200807",
    "skuName": "BISONOL 5 MG TABLET 10",
    "composition": "BISOPROLOL TABLET 5 MG",
    "packSize": "10 TABLET",
    "dosageForm": "TABLET",
    "ceilingPrice": "-1",
    "company": "KNOLL HEALTHCARE PVT.LTD",
    "scheduleFlag": "0",
    "mrp": "45.00",
    "scheduleStatus": "Non-Scheduled",
    "yearMonth": "Dec-2025",
    "mrpPerUnit": "4.50"
  },
  {
    "hiddenId": "1521152436@339956@101229216@3311@101006@200807",
    "skuName": "BISOPER 2.5 MG TABLET 10",
    "composition": "BISOPROLOL TABLET 2.5 MG",
    "packSize": "10 TABLET",
    "dosageForm": "TABLET",
    "ceilingPrice": "-1",
    "company": "ESWAR THERAPEUTICS PVT.LTD",
    "scheduleFlag": "0",
    "mrp": "100.30",
    "scheduleStatus": "Non-Scheduled",
    "yearMonth": "Dec-2025",
    "mrpPerUnit": "10.03"
  },
  {
    "hiddenId": "1521152430@339955@101229216@3854@101006@200807",
    "skuName": "BISOPER 5 MG TABLET 10",
    "composition": "BISOPROLOL TABLET 5 MG",
    "packSize": "10 TABLET",
    "dosageForm": "TABLET",
    "ceilingPrice": "-1",
    "company": "ESWAR THERAPEUTICS PVT.LTD",
    "scheduleFlag": "0",
    "mrp": "112.50",
    "scheduleStatus": "Non-Scheduled",
    "yearMonth": "Dec-2025",
    "mrpPerUnit": "11.25"
  },
  {
    "hiddenId": "1521098376@350570@101247420@2401@101006@200807",
    "skuName": "BISOPHARM 1.25 MG TABLET 10",
    "composition": "BISOPROLOL TABLET 1.25 MG",
    "packSize": "10 TABLET",
    "dosageForm": "TABLET",
    "ceilingPrice": "-1",
    "company": "ERIS LIFESCIENCES LTD",
    "scheduleFlag": "0",
    "mrp": "50.53",
    "scheduleStatus": "Non-Scheduled",
    "yearMonth": "Dec-2025",
    "mrpPerUnit": "5.05"
  },
  {
    "hiddenId": "1521098377@350571@101247420@3311@101006@200807",
    "skuName": "BISOPHARM 2.5 MG TABLET 10",
    "composition": "BISOPROLOL TABLET 2.5 MG",
    "packSize": "10 TABLET",
    "dosageForm": "TABLET",
    "ceilingPrice": "-1",
    "company": "ERIS LIFESCIENCES LTD",
    "scheduleFlag": "0",
    "mrp": "60.84",
    "scheduleStatus": "Non-Scheduled",
    "yearMonth": "Dec-2025",
    "mrpPerUnit": "6.08"
  },
  {
    "hiddenId": "1521098681@350569@101247420@3854@101006@200807",
    "skuName": "BISOPHARM 5 MG TABLET 10",
    "composition": "BISOPROLOL TABLET 5 MG",
    "packSize": "10 TABLET",
    "dosageForm": "TABLET",
    "ceilingPrice": "-1",
    "company": "ERIS LIFESCIENCES LTD",
    "scheduleFlag": "0",
    "mrp": "109.31",
    "scheduleStatus": "Non-Scheduled",
    "yearMonth": "Dec-2025",
    "mrpPerUnit": "10.93"
  },
  {
    "hiddenId": "1521136681@9999996432@101240931@3311@101006@200807",
    "skuName": "BISOREG 2.5 MG TABLET 10",
    "composition": "BISOPROLOL TABLET 2.5 MG",
    "packSize": "10 TABLET",
    "dosageForm": "TABLET",
    "ceilingPrice": "-1",
    "company": "EXELTIS",
    "scheduleFlag": "0",
    "mrp": "87.26",
    "scheduleStatus": "Non-Scheduled",
    "yearMonth": "Dec-2025",
    "mrpPerUnit": "8.73"
  },
  {
    "hiddenId": "1521136703@9999996431@101240931@3854@101006@200807",
    "skuName": "BISOREG 5 MG TABLET 10",
    "composition": "BISOPROLOL TABLET 5 MG",
    "packSize": "10 TABLET",
    "dosageForm": "TABLET",
    "ceilingPrice": "-1",
    "company": "EXELTIS",
    "scheduleFlag": "0",
    "mrp": "112.50",
    "scheduleStatus": "Non-Scheduled",
    "yearMonth": "Dec-2025",
    "mrpPerUnit": "11.25"
  },
  {
    "hiddenId": "1521137756@353841@101229219@3854@101006@200807",
    "skuName": "BISORIDE 5 MG TABLET 10",
    "composition": "BISOPROLOL TABLET 5 MG",
    "packSize": "10 TABLET",
    "dosageForm": "TABLET",
    "ceilingPrice": "-1",
    "company": "UNISON PHARMACEUTICALS",
    "scheduleFlag": "0",
    "mrp": "20.00",
    "scheduleStatus": "Non-Scheduled",
    "yearMonth": "Dec-2025",
    "mrpPerUnit": "2.00"
  },
  {
    "hiddenId": "1521092119@282082@101158185@3311@101006@200807",
    "skuName": "BISOSAFE 2.5 MG TABLET 10",
    "composition": "BISOPROLOL TABLET 2.5 MG",
    "packSize": "10 TABLET",
    "dosageForm": "TABLET",
    "ceilingPrice": "-1",
    "company": "ABBOTT HEALTHCARE PVT. LTD",
    "scheduleFlag": "0",
    "mrp": "68.61",
    "scheduleStatus": "Non-Scheduled",
    "yearMonth": "Dec-2025",
    "mrpPerUnit": "6.86"
  },
  {
    "hiddenId": "1521092120@282084@101158185@3854@101006@200807",
    "skuName": "BISOSAFE 5 MG TABLET 10",
    "composition": "BISOPROLOL TABLET 5 MG",
    "packSize": "10 TABLET",
    "dosageForm": "TABLET",
    "ceilingPrice": "-1",
    "company": "ABBOTT HEALTHCARE PVT. LTD",
    "scheduleFlag": "0",
    "mrp": "105.66",
    "scheduleStatus": "Non-Scheduled",
    "yearMonth": "Dec-2025",
    "mrpPerUnit": "10.57"
  },
  {
    "hiddenId": "1521139074@9999998740@101229220@3311@101006@200807",
    "skuName": "BISOSON 2.5 MG TABLET 10",
    "composition": "BISOPROLOL TABLET 2.5 MG",
    "packSize": "10 TABLET",
    "dosageForm": "TABLET",
    "ceilingPrice": "-1",
    "company": "UNISON PHARMACEUTICALS",
    "scheduleFlag": "0",
    "mrp": "16.88",
    "scheduleStatus": "Non-Scheduled",
    "yearMonth": "Dec-2025",
    "mrpPerUnit": "1.69"
  },
  {
    "hiddenId": "1521148847@9999998739@101229220@3854@101006@200807",
    "skuName": "BISOSON 5 MG TABLET 10",
    "composition": "BISOPROLOL TABLET 5 MG",
    "packSize": "10 TABLET",
    "dosageForm": "TABLET",
    "ceilingPrice": "-1",
    "company": "UNISON PHARMACEUTICALS",
    "scheduleFlag": "0",
    "mrp": "18.75",
    "scheduleStatus": "Non-Scheduled",
    "yearMonth": "Dec-2025",
    "mrpPerUnit": "1.88"
  },
  {
    "hiddenId": "1521055320@287753@101158253@3311@101006@200807",
    "skuName": "BISOTAB 2.5 MG TABLET 10",
    "composition": "BISOPROLOL TABLET 2.5 MG",
    "packSize": "10 TABLET",
    "dosageForm": "TABLET",
    "ceilingPrice": "-1",
    "company": "JB CHEMICALS",
    "scheduleFlag": "0",
    "mrp": "86.92",
    "scheduleStatus": "Non-Scheduled",
    "yearMonth": "Dec-2025",
    "mrpPerUnit": "8.69"
  },
  {
    "hiddenId": "1521055609@287752@101158253@3854@101006@200807",
    "skuName": "BISOTAB 5 MG TABLET 10",
    "composition": "BISOPROLOL TABLET 5 MG",
    "packSize": "10 TABLET",
    "dosageForm": "TABLET",
    "ceilingPrice": "-1",
    "company": "JB CHEMICALS",
    "scheduleFlag": "0",
    "mrp": "128.32",
    "scheduleStatus": "Non-Scheduled",
    "yearMonth": "Dec-2025",
    "mrpPerUnit": "12.83"
  },
  {
    "hiddenId": "1521133679@9999999740@101224287@3311@101006@200807",
    "skuName": "BISOTRAK 2.5 MG TABLET 10",
    "composition": "BISOPROLOL TABLET 2.5 MG",
    "packSize": "10 TABLET",
    "dosageForm": "TABLET",
    "ceilingPrice": "-1",
    "company": "ZUVENTUS HEALTHCARE LTD",
    "scheduleFlag": "0",
    "mrp": "37.50",
    "scheduleStatus": "Non-Scheduled",
    "yearMonth": "Dec-2025",
    "mrpPerUnit": "3.75"
  },
  {
    "hiddenId": "1521133680@9999999739@101224287@3854@101006@200807",
    "skuName": "BISOTRAK 5 MG TABLET 10",
    "composition": "BISOPROLOL TABLET 5 MG",
    "packSize": "10 TABLET",
    "dosageForm": "TABLET",
    "ceilingPrice": "-1",
    "company": "ZUVENTUS HEALTHCARE LTD",
    "scheduleFlag": "0",
    "mrp": "46.85",
    "scheduleStatus": "Non-Scheduled",
    "yearMonth": "Dec-2025",
    "mrpPerUnit": "4.69"
  },
  {
    "hiddenId": "1521137502@9999999768@101229223@3311@101006@200807",
    "skuName": "BISOVAS 2.5 MG TABLET 10",
    "composition": "BISOPROLOL TABLET 2.5 MG",
    "packSize": "10 TABLET",
    "dosageForm": "TABLET",
    "ceilingPrice": "-1",
    "company": "WALRON HEALTHCARE PVT.LTD",
    "scheduleFlag": "0",
    "mrp": "52.50",
    "scheduleStatus": "Non-Scheduled",
    "yearMonth": "Dec-2025",
    "mrpPerUnit": "5.25"
  },
  {
    "hiddenId": "1521142264@9999999767@101229223@3854@101006@200807",
    "skuName": "BISOVAS 5 MG TABLET 10",
    "composition": "BISOPROLOL TABLET 5 MG",
    "packSize": "10 TABLET",
    "dosageForm": "TABLET",
    "ceilingPrice": "-1",
    "company": "WALRON HEALTHCARE PVT.LTD",
    "scheduleFlag": "0",
    "mrp": "63.75",
    "scheduleStatus": "Non-Scheduled",
    "yearMonth": "Dec-2025",
    "mrpPerUnit": "6.38"
  },
  {
    "hiddenId": "1521141507@350586@101229225@3311@101006@200807",
    "skuName": "BISOWEL 2.5 MG TABLET 10",
    "composition": "BISOPROLOL TABLET 2.5 MG",
    "packSize": "10 TABLET",
    "dosageForm": "TABLET",
    "ceilingPrice": "-1",
    "company": "ARRIENT HEALTHCARE PVT.LTD.",
    "scheduleFlag": "0",
    "mrp": "70.00",
    "scheduleStatus": "Non-Scheduled",
    "yearMonth": "Dec-2025",
    "mrpPerUnit": "7.00"
  },
  {
    "hiddenId": "1521141463@350585@101229225@3854@101006@200807",
    "skuName": "BISOWEL 5 MG TABLET 10",
    "composition": "BISOPROLOL TABLET 5 MG",
    "packSize": "10 TABLET",
    "dosageForm": "TABLET",
    "ceilingPrice": "-1",
    "company": "ARRIENT HEALTHCARE PVT.LTD.",
    "scheduleFlag": "0",
    "mrp": "83.44",
    "scheduleStatus": "Non-Scheduled",
    "yearMonth": "Dec-2025",
    "mrpPerUnit": "8.34"
  },
  {
    "hiddenId": "1521101868@353127@101194670@3311@101006@200807",
    "skuName": "BISOZIFF 2.5 MG TABLET 10",
    "composition": "BISOPROLOL TABLET 2.5 MG",
    "packSize": "10 TABLET",
    "dosageForm": "TABLET",
    "ceilingPrice": "-1",
    "company": "ALEMBIC LTD",
    "scheduleFlag": "0",
    "mrp": "45.00",
    "scheduleStatus": "Non-Scheduled",
    "yearMonth": "Dec-2025",
    "mrpPerUnit": "4.50"
  },
  {
    "hiddenId": "1521101869@353172@101194670@3854@101006@200807",
    "skuName": "BISOZIFF 5 MG TABLET 10",
    "composition": "BISOPROLOL TABLET 5 MG",
    "packSize": "10 TABLET",
    "dosageForm": "TABLET",
    "ceilingPrice": "-1",
    "company": "ALEMBIC LTD",
    "scheduleFlag": "0",
    "mrp": "60.00",
    "scheduleStatus": "Non-Scheduled",
    "yearMonth": "Dec-2025",
    "mrpPerUnit": "6.00"
  },
  {
    "hiddenId": "1521155250@9999994825@101242284@3311@101006@200807",
    "skuName": "BISOZOX 2.5 MG TABLET 15",
    "composition": "BISOPROLOL TABLET 2.5 MG",
    "packSize": "15 TABLET",
    "dosageForm": "TABLET",
    "ceilingPrice": "-1",
    "company": "LLOYD HEALTHCARE PVT.LTD",
    "scheduleFlag": "0",
    "mrp": "84.38",
    "scheduleStatus": "Non-Scheduled",
    "yearMonth": "Dec-2025",
    "mrpPerUnit": "5.63"
  },
  {
    "hiddenId": "1521155252@9999994826@101242284@3854@101006@200807",
    "skuName": "BISOZOX 5 MG TABLET 15",
    "composition": "BISOPROLOL TABLET 5 MG",
    "packSize": "15 TABLET",
    "dosageForm": "TABLET",
    "ceilingPrice": "-1",
    "company": "LLOYD HEALTHCARE PVT.LTD",
    "scheduleFlag": "0",
    "mrp": "112.50",
    "scheduleStatus": "Non-Scheduled",
    "yearMonth": "Dec-2025",
    "mrpPerUnit": "7.50"
  },
  {
    "hiddenId": "1521012231@196284@101104750@2107@101006@200807",
    "skuName": "BISVEDA 10 MG TABLET 10",
    "composition": "BISOPROLOL TABLET 10 MG",
    "packSize": "10 TABLET",
    "dosageForm": "TABLET",
    "ceilingPrice": "-1",
    "company": "KEPLER HEALTH CARE",
    "scheduleFlag": "0",
    "mrp": "96.00",
    "scheduleStatus": "Non-Scheduled",
    "yearMonth": "Dec-2025",
    "mrpPerUnit": "9.60"
  },
  {
    "hiddenId": "1521008040@196285@101104750@3311@101006@200807",
    "skuName": "BISVEDA 2.5 MG TABLET 10",
    "composition": "BISOPROLOL TABLET 2.5 MG",
    "packSize": "10 TABLET",
    "dosageForm": "TABLET",
    "ceilingPrice": "-1",
    "company": "KEPLER HEALTH CARE",
    "scheduleFlag": "0",
    "mrp": "46.88",
    "scheduleStatus": "Non-Scheduled",
    "yearMonth": "Dec-2025",
    "mrpPerUnit": "4.69"
  },
  {
    "hiddenId": "1521012232@196286@101104750@3854@101006@200807",
    "skuName": "BISVEDA 5 MG TABLET 10",
    "composition": "BISOPROLOL TABLET 5 MG",
    "packSize": "10 TABLET",
    "dosageForm": "TABLET",
    "ceilingPrice": "-1",
    "company": "KEPLER HEALTH CARE",
    "scheduleFlag": "0",
    "mrp": "73.00",
    "scheduleStatus": "Non-Scheduled",
    "yearMonth": "Dec-2025",
    "mrpPerUnit": "7.30"
  },
  {
    "hiddenId": "1521159404@703737@101244829@2107@101006@200807",
    "skuName": "BITAB 10 MG TABLET 15",
    "composition": "BISOPROLOL TABLET 10 MG",
    "packSize": "15 TABLET",
    "dosageForm": "TABLET",
    "ceilingPrice": "-1",
    "company": "ALTEUS BIOGENICS PVT.LTD.",
    "scheduleFlag": "0",
    "mrp": "79.01",
    "scheduleStatus": "Non-Scheduled",
    "yearMonth": "Dec-2025",
    "mrpPerUnit": "5.27"
  },
  {
    "hiddenId": "1521159289@703606@101244829@2401@101006@200807",
    "skuName": "BITAB 1.25 MG TABLET 15",
    "composition": "BISOPROLOL TABLET 1.25 MG",
    "packSize": "15 TABLET",
    "dosageForm": "TABLET",
    "ceilingPrice": "-1",
    "company": "ALTEUS BIOGENICS PVT.LTD.",
    "scheduleFlag": "0",
    "mrp": "49.22",
    "scheduleStatus": "Non-Scheduled",
    "yearMonth": "Dec-2025",
    "mrpPerUnit": "3.28"
  },
  {
    "hiddenId": "1521158800@703608@101244829@3311@101006@200807",
    "skuName": "BITAB 2.5 MG TABLET 15",
    "composition": "BISOPROLOL TABLET 2.5 MG",
    "packSize": "15 TABLET",
    "dosageForm": "TABLET",
    "ceilingPrice": "-1",
    "company": "ALTEUS BIOGENICS PVT.LTD.",
    "scheduleFlag": "0",
    "mrp": "63.28",
    "scheduleStatus": "Non-Scheduled",
    "yearMonth": "Dec-2025",
    "mrpPerUnit": "4.22"
  },
  {
    "hiddenId": "1521158801@703738@101244829@3854@101006@200807",
    "skuName": "BITAB 5 MG TABLET 15",
    "composition": "BISOPROLOL TABLET 5 MG",
    "packSize": "15 TABLET",
    "dosageForm": "TABLET",
    "ceilingPrice": "-1",
    "company": "ALTEUS BIOGENICS PVT.LTD.",
    "scheduleFlag": "0",
    "mrp": "68.91",
    "scheduleStatus": "Non-Scheduled",
    "yearMonth": "Dec-2025",
    "mrpPerUnit": "4.59"
  },
  {
    "hiddenId": "1521160001@704628@101245870@-1@101006@200807",
    "skuName": "BIXIJOY TABLET 10",
    "composition": "BISOPROLOL TABLET ",
    "packSize": "10 TABLET",
    "dosageForm": "TABLET",
    "ceilingPrice": "-1",
    "company": "ZYDUS HEALTHCARE LTD.",
    "scheduleFlag": "0",
    "mrp": "220.00",
    "scheduleStatus": "Non-Scheduled",
    "yearMonth": "Dec-2025",
    "mrpPerUnit": "22.00"
  },
  {
    "hiddenId": "1521092125@318842@101104787@3311@101006@200807",
    "skuName": "BIZO 2.5 MG TABLET 10",
    "composition": "BISOPROLOL TABLET 2.5 MG",
    "packSize": "10 TABLET",
    "dosageForm": "TABLET",
    "ceilingPrice": "-1",
    "company": "SPECTRA THERAPEUTICS PVT. LTD.",
    "scheduleFlag": "0",
    "mrp": "43.22",
    "scheduleStatus": "Non-Scheduled",
    "yearMonth": "Dec-2025",
    "mrpPerUnit": "4.32"
  },
  {
    "hiddenId": "1521092121@318843@101104787@3854@101006@200807",
    "skuName": "BIZO 5 MG TABLET 10",
    "composition": "BISOPROLOL TABLET 5 MG",
    "packSize": "10 TABLET",
    "dosageForm": "TABLET",
    "ceilingPrice": "-1",
    "company": "SPECTRA THERAPEUTICS PVT. LTD.",
    "scheduleFlag": "0",
    "mrp": "51.38",
    "scheduleStatus": "Non-Scheduled",
    "yearMonth": "Dec-2025",
    "mrpPerUnit": "5.14"
  },
  {
    "hiddenId": "1521103314@354183@101195250@2107@101006@200807",
    "skuName": "BLOCPRO 10 MG TABLET 10",
    "composition": "BISOPROLOL TABLET 10 MG",
    "packSize": "10 TABLET",
    "dosageForm": "TABLET",
    "ceilingPrice": "-1",
    "company": "IPCA LABORATORIES PVT LTD.",
    "scheduleFlag": "0",
    "mrp": "103.08",
    "scheduleStatus": "Non-Scheduled",
    "yearMonth": "Dec-2025",
    "mrpPerUnit": "10.31"
  },
  {
    "hiddenId": "1521103309@354181@101195250@2401@101006@200807",
    "skuName": "BLOCPRO 1.25 MG TABLET 10",
    "composition": "BISOPROLOL TABLET 1.25 MG",
    "packSize": "10 TABLET",
    "dosageForm": "TABLET",
    "ceilingPrice": "-1",
    "company": "IPCA LABORATORIES PVT LTD.",
    "scheduleFlag": "0",
    "mrp": "60.05",
    "scheduleStatus": "Non-Scheduled",
    "yearMonth": "Dec-2025",
    "mrpPerUnit": "6.01"
  },
  {
    "hiddenId": "1521103310@354184@101195250@3311@101006@200807",
    "skuName": "BLOCPRO 2.5 MG TABLET 10",
    "composition": "BISOPROLOL TABLET 2.5 MG",
    "packSize": "10 TABLET",
    "dosageForm": "TABLET",
    "ceilingPrice": "-1",
    "company": "IPCA LABORATORIES PVT LTD.",
    "scheduleFlag": "0",
    "mrp": "65.95",
    "scheduleStatus": "Non-Scheduled",
    "yearMonth": "Dec-2025",
    "mrpPerUnit": "6.60"
  },
  {
    "hiddenId": "1521103334@354185@101195250@3854@101006@200807",
    "skuName": "BLOCPRO 5 MG TABLET 10",
    "composition": "BISOPROLOL TABLET 5 MG",
    "packSize": "10 TABLET",
    "dosageForm": "TABLET",
    "ceilingPrice": "-1",
    "company": "IPCA LABORATORIES PVT LTD.",
    "scheduleFlag": "0",
    "mrp": "87.61",
    "scheduleStatus": "Non-Scheduled",
    "yearMonth": "Dec-2025",
    "mrpPerUnit": "8.76"
  },
  {
    "hiddenId": "1521155883@700381@101242842@2107@101006@200807",
    "skuName": "CARDIBIS 10 MG TABLET 10",
    "composition": "BISOPROLOL TABLET 10 MG",
    "packSize": "10 TABLET",
    "dosageForm": "TABLET",
    "ceilingPrice": "-1",
    "company": "ARISTO PHARMACEUTICALS PVT.LTD",
    "scheduleFlag": "0",
    "mrp": "75.00",
    "scheduleStatus": "Non-Scheduled",
    "yearMonth": "Dec-2025",
    "mrpPerUnit": "7.50"
  },
  {
    "hiddenId": "1521156307@700380@101242842@2401@101006@200807",
    "skuName": "CARDIBIS 1.25 MG TABLET 10",
    "composition": "BISOPROLOL TABLET 1.25 MG",
    "packSize": "10 TABLET",
    "dosageForm": "TABLET",
    "ceilingPrice": "-1",
    "company": "ARISTO PHARMACEUTICALS PVT.LTD",
    "scheduleFlag": "0",
    "mrp": "37.50",
    "scheduleStatus": "Non-Scheduled",
    "yearMonth": "Dec-2025",
    "mrpPerUnit": "3.75"
  },
  {
    "hiddenId": "1521156308@700382@101242842@3311@101006@200807",
    "skuName": "CARDIBIS 2.5 MG TABLET 10",
    "composition": "BISOPROLOL TABLET 2.5 MG",
    "packSize": "10 TABLET",
    "dosageForm": "TABLET",
    "ceilingPrice": "-1",
    "company": "ARISTO PHARMACEUTICALS PVT.LTD",
    "scheduleFlag": "0",
    "mrp": "42.18",
    "scheduleStatus": "Non-Scheduled",
    "yearMonth": "Dec-2025",
    "mrpPerUnit": "4.22"
  },
  {
    "hiddenId": "1521156309@700383@101242842@3854@101006@200807",
    "skuName": "CARDIBIS 5 MG TABLET 10",
    "composition": "BISOPROLOL TABLET 5 MG",
    "packSize": "10 TABLET",
    "dosageForm": "TABLET",
    "ceilingPrice": "-1",
    "company": "ARISTO PHARMACEUTICALS PVT.LTD",
    "scheduleFlag": "0",
    "mrp": "60.93",
    "scheduleStatus": "Non-Scheduled",
    "yearMonth": "Dec-2025",
    "mrpPerUnit": "6.09"
  },
  {
    "hiddenId": "1521013836@43533@101119262@2107@101006@200807",
    "skuName": "CONCOR 10 MG TABLET 10",
    "composition": "BISOPROLOL TABLET 10 MG",
    "packSize": "10 TABLET",
    "dosageForm": "TABLET",
    "ceilingPrice": "-1",
    "company": "MERCK SPECIALITIES PVT.LTD",
    "scheduleFlag": "0",
    "mrp": "223.80",
    "scheduleStatus": "Non-Scheduled",
    "yearMonth": "Dec-2025",
    "mrpPerUnit": "22.38"
  },
  {
    "hiddenId": "1521057750@43534@101119262@3854@101006@200807",
    "skuName": "CONCOR 5 MG TABLET 10",
    "composition": "BISOPROLOL TABLET 5 MG",
    "packSize": "10 TABLET",
    "dosageForm": "TABLET",
    "ceilingPrice": "-1",
    "company": "MERCK SPECIALITIES PVT.LTD",
    "scheduleFlag": "0",
    "mrp": "132.18",
    "scheduleStatus": "Non-Scheduled",
    "yearMonth": "Dec-2025",
    "mrpPerUnit": "13.22"
  },
  {
    "hiddenId": "1521013839@166587@101119275@2401@101006@200807",
    "skuName": "CONCOR COR 1.25 MG TABLET 10",
    "composition": "BISOPROLOL TABLET 1.25 MG",
    "packSize": "10 TABLET",
    "dosageForm": "TABLET",
    "ceilingPrice": "-1",
    "company": "MERCK SPECIALITIES PVT.LTD",
    "scheduleFlag": "0",
    "mrp": "72.30",
    "scheduleStatus": "Non-Scheduled",
    "yearMonth": "Dec-2025",
    "mrpPerUnit": "7.23"
  },
  {
    "hiddenId": "1521057792@43531@101119275@3311@101006@200807",
    "skuName": "CONCOR COR 2.5 MG TABLET 10",
    "composition": "BISOPROLOL TABLET 2.5 MG",
    "packSize": "10 TABLET",
    "dosageForm": "TABLET",
    "ceilingPrice": "-1",
    "company": "MERCK SPECIALITIES PVT.LTD",
    "scheduleFlag": "0",
    "mrp": "88.55",
    "scheduleStatus": "Non-Scheduled",
    "yearMonth": "Dec-2025",
    "mrpPerUnit": "8.86"
  },
  {
    "hiddenId": "1521093422@331077@101189771@3311@101006@200807",
    "skuName": "CONCOVAS 2.5 MG TABLET 10",
    "composition": "BISOPROLOL TABLET 2.5 MG",
    "packSize": "10 TABLET",
    "dosageForm": "TABLET",
    "ceilingPrice": "-1",
    "company": "VASU ORGANICS PVT.LTD",
    "scheduleFlag": "0",
    "mrp": "75.09",
    "scheduleStatus": "Non-Scheduled",
    "yearMonth": "Dec-2025",
    "mrpPerUnit": "7.51"
  },
  {
    "hiddenId": "1521093986@331076@101189771@3854@101006@200807",
    "skuName": "CONCOVAS 5 MG TABLET 10",
    "composition": "BISOPROLOL TABLET 5 MG",
    "packSize": "10 TABLET",
    "dosageForm": "TABLET",
    "ceilingPrice": "-1",
    "company": "VASU ORGANICS PVT.LTD",
    "scheduleFlag": "0",
    "mrp": "98.38",
    "scheduleStatus": "Non-Scheduled",
    "yearMonth": "Dec-2025",
    "mrpPerUnit": "9.84"
  },
  {
    "hiddenId": "1521059684@68227@101119563@2107@101006@200807",
    "skuName": "CORBIS 10 MG TABLET 10",
    "composition": "BISOPROLOL TABLET 10 MG",
    "packSize": "10 TABLET",
    "dosageForm": "TABLET",
    "ceilingPrice": "-1",
    "company": "TORRENT PHARMACEUTICALS LTD.",
    "scheduleFlag": "0",
    "mrp": "129.80",
    "scheduleStatus": "Non-Scheduled",
    "yearMonth": "Dec-2025",
    "mrpPerUnit": "12.98"
  },
  {
    "hiddenId": "1521156115@700260@101119563@2107@101006@200807",
    "skuName": "CORBIS 10 MG TABLET 15",
    "composition": "BISOPROLOL TABLET 10 MG",
    "packSize": "15 TABLET",
    "dosageForm": "TABLET",
    "ceilingPrice": "-1",
    "company": "TORRENT PHARMACEUTICALS LTD.",
    "scheduleFlag": "0",
    "mrp": "102.59",
    "scheduleStatus": "Non-Scheduled",
    "yearMonth": "Dec-2025",
    "mrpPerUnit": "6.84"
  },
  {
    "hiddenId": "1521013901@307798@101119563@2401@101006@200807",
    "skuName": "CORBIS 1.25 MG TABLET 15",
    "composition": "BISOPROLOL TABLET 1.25 MG",
    "packSize": "15 TABLET",
    "dosageForm": "TABLET",
    "ceilingPrice": "-1",
    "company": "TORRENT PHARMACEUTICALS LTD.",
    "scheduleFlag": "0",
    "mrp": "67.60",
    "scheduleStatus": "Non-Scheduled",
    "yearMonth": "Dec-2025",
    "mrpPerUnit": "4.51"
  },
  {
    "hiddenId": "1521059700@224073@101119563@3311@101006@200807",
    "skuName": "CORBIS 2.5 MG TABLET 15",
    "composition": "BISOPROLOL TABLET 2.5 MG",
    "packSize": "15 TABLET",
    "dosageForm": "TABLET",
    "ceilingPrice": "-1",
    "company": "TORRENT PHARMACEUTICALS LTD.",
    "scheduleFlag": "0",
    "mrp": "105.15",
    "scheduleStatus": "Non-Scheduled",
    "yearMonth": "Dec-2025",
    "mrpPerUnit": "7.01"
  },
  {
    "hiddenId": "1521059737@222074@101119563@3854@101006@200807",
    "skuName": "CORBIS 5 MG TABLET 15",
    "composition": "BISOPROLOL TABLET 5 MG",
    "packSize": "15 TABLET",
    "dosageForm": "TABLET",
    "ceilingPrice": "-1",
    "company": "TORRENT PHARMACEUTICALS LTD.",
    "scheduleFlag": "0",
    "mrp": "126.55",
    "scheduleStatus": "Non-Scheduled",
    "yearMonth": "Dec-2025",
    "mrpPerUnit": "8.44"
  },
  {
    "hiddenId": "1521094481@343069@101190407@-1@101038@200807",
    "skuName": "PROBASE V CAPSULE 10",
    "composition": "BISOPROLOL CAPSULE ",
    "packSize": "10 CAPSULE",
    "dosageForm": "CAPSULE",
    "ceilingPrice": "-1",
    "company": "BESTOCHEM FORMULATIONS (I) LTD",
    "scheduleFlag": "0",
    "mrp": "121.88",
    "scheduleStatus": "Non-Scheduled",
    "yearMonth": "Dec-2025",
    "mrpPerUnit": "12.19"
  },
  {
    "hiddenId": "1521151120@9999998633@101237149@3311@101006@200807",
    "skuName": "PROSKY 2.5 MG TABLET 10",
    "composition": "BISOPROLOL TABLET 2.5 MG",
    "packSize": "10 TABLET",
    "dosageForm": "TABLET",
    "ceilingPrice": "-1",
    "company": "NIRVANA HEALTH CARE",
    "scheduleFlag": "0",
    "mrp": "48.00",
    "scheduleStatus": "Non-Scheduled",
    "yearMonth": "Dec-2025",
    "mrpPerUnit": "4.80"
  },
  {
    "hiddenId": "1521153934@9999998632@101237149@3854@101006@200807",
    "skuName": "PROSKY 5 MG TABLET 10",
    "composition": "BISOPROLOL TABLET 5 MG",
    "packSize": "10 TABLET",
    "dosageForm": "TABLET",
    "ceilingPrice": "-1",
    "company": "NIRVANA HEALTH CARE",
    "scheduleFlag": "0",
    "mrp": "60.00",
    "scheduleStatus": "Non-Scheduled",
    "yearMonth": "Dec-2025",
    "mrpPerUnit": "6.00"
  },
  {
    "hiddenId": "1521105704@81690@101225663@3311@101006@200807",
    "skuName": "TRUBIS 2.5 MG TABLET 10",
    "composition": "BISOPROLOL TABLET 2.5 MG",
    "packSize": "10 TABLET",
    "dosageForm": "TABLET",
    "ceilingPrice": "-1",
    "company": "TORRENT PHARMACEUTICALS LTD.",
    "scheduleFlag": "0",
    "mrp": "30.53",
    "scheduleStatus": "Non-Scheduled",
    "yearMonth": "Dec-2025",
    "mrpPerUnit": "3.05"
  },
  {
    "hiddenId": "1521084626@62555@101185402@3854@101006@200807",
    "skuName": "ZABESTA 5 MG TABLET 10",
    "composition": "BISOPROLOL TABLET 5 MG",
    "packSize": "10 TABLET",
    "dosageForm": "TABLET",
    "ceilingPrice": "-1",
    "company": "USV PVT LTD",
    "scheduleFlag": "0",
    "mrp": "69.20",
    "scheduleStatus": "Non-Scheduled",
    "yearMonth": "Dec-2025",
    "mrpPerUnit": "6.92"
  }
]